Workbook

Sheet Sheet2
A1: Order ID | B1: Order Date
A2: 10005 | B2: =VLOOKUP(Sheet2!A2,Sheet1!$A$1:$R$373,3,0) -> 45241
A3: 10010 | B3: =VLOOKUP(Sheet2!A3,Sheet1!$A$1:$R$373,3,0) -> 45139
A4: 10017 | B4: =VLOOKUP(Sheet2!A4,Sheet1!$A$1:$R$373,3,0) -> 45148
A5: 10022 | B5: =VLOOKUP(Sheet2!A5,Sheet1!$A$1:$R$373,3,0) -> 44944
A6: 10025 | B6: =VLOOKUP(Sheet2!A6,Sheet1!$A$1:$R$373,3,0) -> 45052

Sheet Sheet1
A1: Order ID | B1: Customer ID | C1: Order Date | D1: Ship Date | E1: City | F1: State | G1: Sales Channel | H1: Payment Method | I1: Product Category | J1: Product Name | K1: Brand | L1: Units Sold | M1: Unit Price | N1: Discount % | O1: Total Price | P1: Price Category | Q1: Discount Category | R1: Unit Category | T1: Order ID | U1: Units Sold
A2: 10001 | B2: 1102 | C2: 45197 | D2: 45203 | E2: Chennai | F2: Delhi | G2: Mobile App | H2: Credit Card | I2: Home & Kitchen | J2: Mixer Grinder | K2: BrandA | L2: 7 | M2: 2843.87 | N2: 0 | O2: =L2*M2 -> 19907.09 | P2: =IF(O2>=15000,"High price","Low price") -> High price | Q2: {=_xlfn.IFS(N2>=10,"HIGH",N2>=5,"MEDIUM",N2<5,"LOW")} -> LOW | R2: =IF(L2>8,"High",IF(L2>4,"Medium","Low")) -> Medium | T2: 10009 | U2: =VLOOKUP(T2,A1:R373,12,0) -> 5
A3: 10002 | B3: 1435 | C3: 45199 | D3: 45203 | E3: Pune | F3: Tamil Nadu | G3: Website | H3: Debit Card | I3: Sports | J3: Football | K3: BrandD | L3: 9 | M3: 2525.23 | N3: 5 | O3: =L3*M3 -> 22727.07 | P3: =IF(O3>=15000,"High price","Low price") -> High price | Q3: {=_xlfn.IFS(N3>=10,"HIGH",N3>=5,"MEDIUM",N3<5,"LOW")} -> MEDIUM | R3: =IF(L3>8,"High",IF(L3>4,"Medium","Low")) -> High | T3: Customer ID | U3: Product Name
A4: 10003 | B4: 1860 | C4: 45109 | D4: 45114 | E4: Chennai | F4: West Bengal | G4: Marketplace | H4: Debit Card | I4: Fashion | J4: Sneakers | K4: BrandE | L4: 6 | M4: 3474.34 | N4: 15 | O4: =L4*M4 -> 20846.04 | P4: =IF(O4>=15000,"High price","Low price") -> High price | Q4: {=_xlfn.IFS(N4>=10,"HIGH",N4>=5,"MEDIUM",N4<5,"LOW")} -> HIGH | R4: =IF(L4>8,"High",IF(L4>4,"Medium","Low")) -> Medium | T4: 1860 | U4: =VLOOKUP(T4,B1:R373,9,0) -> Sneakers
A5: 10004 | B5: 1270 | C5: 45079 | D5: 45087 | E5: Bengaluru | F5: West Bengal | G5: Website | H5: Cash on Delivery | I5: Sports | J5: Yoga Mat | K5: BrandA | L5: 1 | M5: 1008.79 | N5: 15 | O5: =L5*M5 -> 1008.79 | P5: =IF(O5>=15000,"High price","Low price") -> Low price | Q5: {=_xlfn.IFS(N5>=10,"HIGH",N5>=5,"MEDIUM",N5<5,"LOW")} -> HIGH | R5: =IF(L5>8,"High",IF(L5>4,"Medium","Low")) -> Low
A6: 10005 | B6: 1106 | C6: 45241 | D6: 45244 | E6: Kolkata | F6: Karnataka | G6: Marketplace | H6: Credit Card | I6: Fashion | J6: Jacket | K6: BrandA | L6: 7 | M6: 3511.47 | N6: 20 | O6: =L6*M6 -> 24580.29 | P6: =IF(O6>=15000,"High price","Low price") -> High price | Q6: {=_xlfn.IFS(N6>=10,"HIGH",N6>=5,"MEDIUM",N6<5,"LOW")} -> HIGH | R6: =IF(L6>8,"High",IF(L6>4,"Medium","Low")) -> Medium | T6: Order ID | U6: City | V6: State
A7: 10006 | B7: 1071 | C7: 45260 | D7: 45263 | E7: Hyderabad | F7: Telangana | G7: Website | H7: Net Banking | I7: Home & Kitchen | J7: Bedsheet | K7: BrandE | L7: 3 | M7: 3189.55 | N7: 10 | O7: =L7*M7 -> 9568.65 | P7: =IF(O7>=15000,"High price","Low price") -> Low price | Q7: {=_xlfn.IFS(N7>=10,"HIGH",N7>=5,"MEDIUM",N7<5,"LOW")} -> HIGH | R7: =IF(L7>8,"High",IF(L7>4,"Medium","Low")) -> Low | T7: 10007 | U7: {=VLOOKUP(T7,A1:R373,{5,6},0)} -> Bengaluru | V7: Telangana
A8: 10007 | B8: 1700 | C8: 45050 | D8: 45054 | E8: Bengaluru | F8: Telangana | G8: Mobile App | H8: UPI | I8: Fashion | J8: Sneakers | K8: BrandC | L8: 5 | M8: 3030.42 | N8: 10 | O8: =L8*M8 -> 15152.1 | P8: =IF(O8>=15000,"High price","Low price") -> High price | Q8: {=_xlfn.IFS(N8>=10,"HIGH",N8>=5,"MEDIUM",N8<5,"LOW")} -> HIGH | R8: =IF(L8>8,"High",IF(L8>4,"Medium","Low")) -> Medium
A9: 10008 | B9: 1020 | C9: 45040 | D9: 45041 | E9: Mumbai | F9: Delhi | G9: Website | H9: Credit Card | I9: Fashion | J9: Sneakers | K9: BrandB | L9: 4 | M9: 2310.83 | N9: 10 | O9: =L9*M9 -> 9243.32 | P9: =IF(O9>=15000,"High price","Low price") -> Low price | Q9: {=_xlfn.IFS(N9>=10,"HIGH",N9>=5,"MEDIUM",N9<5,"LOW")} -> HIGH | R9: =IF(L9>8,"High",IF(L9>4,"Medium","Low")) -> Low
A10: 10009 | B10: 1614 | C10: 45204 | D10: 45213 | E10: Chennai | F10: West Bengal | G10: Website | H10: Debit Card | I10: Fashion | J10: T-Shirt | K10: BrandD | L10: 5 | M10: 1098.04 | N10: 15 | O10: =L10*M10 -> 5490.2 | P10: =IF(O10>=15000,"High price","Low price") -> Low price | Q10: {=_xlfn.IFS(N10>=10,"HIGH",N10>=5,"MEDIUM",N10<5,"LOW")} -> HIGH | R10: =IF(L10>8,"High",IF(L10>4,"Medium","Low")) -> Medium
A11: 10010 | B11: 1121 | C11: 45139 | D11: 45147 | E11: Bengaluru | F11: Karnataka | G11: Website | H11: Cash on Delivery | I11: Electronics | J11: Headphones | K11: BrandB | L11: 5 | M11: 1780.66 | N11: 20 | O11: =L11*M11 -> 8903.3 | P11: =IF(O11>=15000,"High price","Low price") -> Low price | Q11: {=_xlfn.IFS(N11>=10,"HIGH",N11>=5,"MEDIUM",N11<5,"LOW")} -> HIGH | R11: =IF(L11>8,"High",IF(L11>4,"Medium","Low")) -> Medium
A12: 10011 | B12: 1466 | C12: 45098 | D12: 45106 | E12: Bengaluru | F12: Karnataka | G12: Mobile App | H12: Cash on Delivery | I12: Electronics | J12: Headphones | K12: BrandE | L12: 6 | M12: 3205.25 | N12: 0 | O12: =L12*M12 -> 19231.5 | P12: =IF(O12>=15000,"High price","Low price") -> High price | Q12: {=_xlfn.IFS(N12>=10,"HIGH",N12>=5,"MEDIUM",N12<5,"LOW")} -> LOW | R12: =IF(L12>8,"High",IF(L12>4,"Medium","Low")) -> Medium
A13: 10012 | B13: 1214 | C13: 45214 | D13: 45220 | E13: Mumbai | F13: Tamil Nadu | G13: Website | H13: UPI | I13: Electronics | J13: Smartwatch | K13: BrandA | L13: 6 | M13: 272.35 | N13: 5 | O13: =L13*M13 -> 1634.1 | P13: =IF(O13>=15000,"High price","Low price") -> Low price | Q13: {=_xlfn.IFS(N13>=10,"HIGH",N13>=5,"MEDIUM",N13<5,"LOW")} -> MEDIUM | R13: =IF(L13>8,"High",IF(L13>4,"Medium","Low")) -> Medium
A14: 10013 | B14: 1330 | C14: 45100 | D14: 45107 | E14: Delhi | F14: Tamil Nadu | G14: Mobile App | H14: Cash on Delivery | I14: Home & Kitchen | J14: Bedsheet | K14: BrandA | L14: 8 | M14: 3160.9 | N14: 0 | O14: =L14*M14 -> 25287.2 | P14: =IF(O14>=15000,"High price","Low price") -> High price | Q14: {=_xlfn.IFS(N14>=10,"HIGH",N14>=5,"MEDIUM",N14<5,"LOW")} -> LOW | R14: =IF(L14>8,"High",IF(L14>4,"Medium","Low")) -> Medium
A15: 10014 | B15: 1458 | C15: 45039 | D15: 45045 | E15: Kolkata | F15: Karnataka | G15: Marketplace | H15: Cash on Delivery | I15: Sports | J15: Yoga Mat | K15: BrandD | L15: 8 | M15: 1074.27 | N15: 15 | O15: =L15*M15 -> 8594.16 | P15: =IF(O15>=15000,"High price","Low price") -> Low price | Q15: {=_xlfn.IFS(N15>=10,"HIGH",N15>=5,"MEDIUM",N15<5,"LOW")} -> HIGH | R15: =IF(L15>8,"High",IF(L15>4,"Medium","Low")) -> Medium
A16: 10015 | B16: 1087 | C16: 45048 | D16: 45057 | E16: Hyderabad | F16: Tamil Nadu | G16: Website | H16: Credit Card | I16: Beauty | J16: Shampoo | K16: BrandA | L16: 9 | M16: 705.59 | N16: 10 | O16: =L16*M16 -> 6350.31 | P16: =IF(O16>=15000,"High price","Low price") -> Low price | Q16: {=_xlfn.IFS(N16>=10,"HIGH",N16>=5,"MEDIUM",N16<5,"LOW")} -> HIGH | R16: =IF(L16>8,"High",IF(L16>4,"Medium","Low")) -> High
A17: 10016 | B17: 1372 | C17: 44958 | D17: 44961 | E17: Pune | F17: West Bengal | G17: Mobile App | H17: Net Banking | I17: Fashion | J17: Jacket | K17: BrandA | L17: 8 | M17: 595.45 | N17: 5 | O17: =L17*M17 -> 4763.6 | P17: =IF(O17>=15000,"High price","Low price") -> Low price | Q17: {=_xlfn.IFS(N17>=10,"HIGH",N17>=5,"MEDIUM",N17<5,"LOW")} -> MEDIUM | R17: =IF(L17>8,"High",IF(L17>4,"Medium","Low")) -> Medium
A18: 10017 | B18: 1099 | C18: 45148 | D18: 45151 | E18: Delhi | F18: Maharashtra | G18: Mobile App | H18: UPI | I18: Fashion | J18: Jacket | K18: BrandD | L18: 2 | M18: 254.91 | N18: 15 | O18: =L18*M18 -> 509.82 | P18: =IF(O18>=15000,"High price","Low price") -> Low price | Q18: {=_xlfn.IFS(N18>=10,"HIGH",N18>=5,"MEDIUM",N18<5,"LOW")} -> HIGH | R18: =IF(L18>8,"High",IF(L18>4,"Medium","Low")) -> Low
A19: 10018 | B19: 1871 | C19: 45045 | D19: 45048 | E19: Chennai | F19: West Bengal | G19: Website | H19: Credit Card | I19: Home & Kitchen | J19: Curtains | K19: BrandD | L19: 1 | M19: 2165.81 | N19: 15 | O19: =L19*M19 -> 2165.81 | P19: =IF(O19>=15000,"High price","Low price") -> Low price | Q19: {=_xlfn.IFS(N19>=10,"HIGH",N19>=5,"MEDIUM",N19<5,"LOW")} -> HIGH | R19: =IF(L19>8,"High",IF(L19>4,"Medium","Low")) -> Low
... A373: 10500 | B373: 1569 | C373: 44972 | D373: 44977 | E373: Chennai | F373: Delhi | G373: Marketplace | H373: Net Banking | I373: Fashion | J373: Jeans | K373: BrandE | L373: 1 | M373: 2432.17 | N373: 20 | O373: =L373*M373 -> 2432.17 | P373: =IF(O373>=15000,"High price","Low price") -> Low price | Q373: {=_xlfn.IFS(N373>=10,"HIGH",N373>=5,"MEDIUM",N373<5,"LOW")} -> HIGH | R373: =IF(L373>8,"High",IF(L373>4,"Medium","Low")) -> Low

Sheet Sheet3
A1: Order ID | B1: 10001 | C1: 10002 | D1: 10003 | E1: 10004 | F1: 10005 | G1: 10006 | H1: 10007 | I1: 10008 | J1: 10009 | K1: 10010 | L1: 10011 | M1: 10012 | N1: 10013 | O1: 10014 | P1: 10015 | Q1: 10016 | R1: 10017 | S1: 10018 | T1: 10019 | U1: 10020 | V1: 10021 | W1: 10022 | X1: 10023 | Y1: 10024 | Z1: 10025 | AA1: 10026 | AB1: 10027 | AC1: 10028 | AD1: 10029 | AE1: 10030 | AF1: 10031 | AG1: 10032 | AH1: 10033 | AI1: 10034 | AJ1: 10035 | AK1: 10036 | AL1: 10037 | AM1: 10038 | AN1: 10039 | AO1: 10040 | AP1: 10041 | AQ1: 10042 | AR1: 10043 | AS1: 10044 | AT1: 10045 | AU1: 10046 | AV1: 10047 | AW1: 10048 | AX1: 10049 | AY1: 10050 | AZ1: 10052 | BA1: 10053 | BB1: 10054 | BC1: 10055 | BD1: 10056 | BE1: 10057 | BF1: 10059 | BG1: 10060 | BH1: 10061 | BI1: 10063 | BJ1: 10064 | BK1: 10065 | BL1: 10066 | BM1: 10067 | BN1: 10068 | BO1: 10069 | BP1: 10070 | BQ1: 10071 | BR1: 10072 | BS1: 10073 | BT1: 10074 | BU1: 10075 | BV1: 10076 | BW1: 10077 | BX1: 10079 | BY1: 10080 | BZ1: 10081 | CA1: 10082 | CB1: 10083 | CC1: 10084 | CD1: 10085 | CE1: 10086 | CF1: 10087 | CG1: 10088 | CH1: 10091 | CI1: 10092 | CJ1: 10093 | CK1: 10094 | CL1: 10095 | CM1: 10096 | CN1: 10097 | CO1: 10098 | CP1: 10099 | CQ1: 10100 | CR1: 10101 | CS1: 10102 | CT1: 10103 | CU1: 10105 | CV1: 10106 | CW1: 10107 | CX1: 10108 | CY1: 10110 | CZ1: 10111 | DA1: 10112 | DB1: 10113 | DC1: 10114 | DD1: 10115 | DE1: 10116 | DF1: 10117 | DG1: 10118 | DH1: 10119 | DI1: 10120 | DJ1: 10121 | DK1: 10122 | DL1: 10123 | DM1: 10124 | DN1: 10125 | DO1: 10126 | DP1: 10127 | DQ1: 10128 | DR1: 10129 | DS1: 10130 | DT1: 10131 | DU1: 10132 | DV1: 10133 | DW1: 10135 | DX1: 10136 | DY1: 10138 | DZ1: 10139 | EA1: 10140 | EB1: 10141 | EC1: 10142 | ED1: 10143 | EE1: 10144 | EF1: 10145 | EG1: 10146 | EH1: 10147 | EI1: 10148 | EJ1: 10149 | EK1: 10150 | EL1: 10151 | EM1: 10152 | EN1: 10154 | EO1: 10155 | EP1: 10156 | EQ1: 10157 | ER1: 10158 | ES1: 10159 | ET1: 10160 | EU1: 10161 | EV1: 10162 | EW1: 10163 | EX1: 10164 | EY1: 10165 | EZ1: 10166 | FA1: 10167 | FB1: 10168 | FC1: 10170 | FD1: 10171 | FE1: 10172 | FF1: 10173 | FG1: 10174 | FH1: 10175 | FI1: 10178 | FJ1: 10179 | FK1: 10180 | FL1: 10181 | FM1: 10183 | FN1: 10184 | FO1: 10185 | FP1: 10186 | FQ1: 10187 | FR1: 10188 | FS1: 10190 | FT1: 10191 | FU1: 10192 | FV1: 10193 | FW1: 10194 | FX1: 10195 | FY1: 10196 | FZ1: 10197 | GA1: 10198 | GB1: 10199 | GC1: 10200 | GD1: 10201 | GE1: 10202 | GF1: 10207 | GG1: 10208 | GH1: 10209 | GI1: 10210 | GJ1: 10211 | GK1: 10212 | GL1: 10214 | GM1: 10215 | GN1: 10216 | GO1: 10217 | GP1: 10218 | GQ1: 10220 | GR1: 10222 | GS1: 10223 | GT1: 10226 | GU1: 10229 | GV1: 10232 | GW1: 10233 | GX1: 10234 | GY1: 10235 | GZ1: 10238 | HA1: 10239 | HB1: 10240 | HC1: 10241 | HD1: 10243 | HE1: 10244 | HF1: 10245 | HG1: 10246 | HH1: 10247 | HI1: 10248 | HJ1: 10249 | HK1: 10251 | HL1: 10252 | HM1: 10253 | HN1: 10254 | HO1: 10257 | HP1: 10260 | HQ1: 10261 | HR1: 10262 | HS1: 10263 | HT1: 10264 | HU1: 10266 | HV1: 10267 | HW1: 10268 | HX1: 10269 | HY1: 10270 | HZ1: 10271 | IA1: 10273 | IB1: 10274 | IC1: 10275 | ID1: 10277 | IE1: 10280 | IF1: 10281 | IG1: 10286 | IH1: 10287 | II1: 10289 | IJ1: 10290 | IK1: 10291 | IL1: 10294 | IM1: 10295 | IN1: 10296 | IO1: 10302 | IP1: 10303 | IQ1: 10304 | IR1: 10305 | IS1: 10306 | IT1: 10307 | IU1: 10308 | IV1: 10309 | IW1: 10311 | IX1: 10312 | IY1: 10313 | IZ1: 10314 | JA1: 10315 | JB1: 10316 | JC1: 10317 | JD1: 10318 | JE1: 10320 | JF1: 10321 | JG1: 10322 | JH1: 10324 | JI1: 10325 | JJ1: 10326 | JK1: 10327 | JL1: 10328 | JM1: 10329 | JN1: 10330 | JO1: 10332 | JP1: 10336 | JQ1: 10338 | JR1: 10339 | JS1: 10341 | JT1: 10342 | JU1: 10343 | JV1: 10344 | JW1: 10345 | JX1: 10347 | JY1: 10350 | JZ1: 10351 | KA1: 10352 | KB1: 10355 | KC1: 10356 | KD1: 10357 | KE1: 10358 | KF1: 10359 | KG1: 10360 | KH1: 10361 | KI1: 10365 | KJ1: 10366 | KK1: 10367 | KL1: 10369 | KM1: 10370 | KN1: 10371 | KO1: 10372 | KP1: 10373 | KQ1: 10374 | KR1: 10376 | KS1: 10379 | KT1: 10381 | KU1: 10383 | KV1: 10384 | KW1: 10385 | KX1: 10386 | KY1: 10387 | KZ1: 10388 | LA1: 10390 | LB1: 10392 | LC1: 10393 | LD1: 10394 | LE1: 10395 | LF1: 10396 | LG1: 10398 | LH1: 10399 | LI1: 10403 | LJ1: 10405 | LK1: 10406 | LL1: 10407 | LM1: 10409 | LN1: 10411 | LO1: 10413 | LP1: 10414 | LQ1: 10417 | LR1: 10418 | LS1: 10422 | LT1: 10423 | LU1: 10427 | LV1: 10431 | LW1: 10434 | LX1: 10435 | LY1: 10436 | LZ1: 10438 | MA1: 10439 | MB1: 10440 | MC1: 10441 | MD1: 10442 | ME1: 10444 | MF1: 10447 | MG1: 10448 | MH1: 10452 | MI1: 10454 | MJ1: 10455 | MK1: 10457 | ML1: 10460 | MM1: 10463 | MN1: 10464 | MO1: 10465 | MP1: 10466 | MQ1: 10468 | MR1: 10470 | MS1: 10472 | MT1: 10480 | MU1: 10481 | MV1: 10482 | MW1: 10485 | MX1: 10486 | MY1: 10487 | MZ1: 10489 | NA1: 10490 | NB1: 10491 | NC1: 10493 | ND1: 10494 | NE1: 10495 | NF1: 10496 | NG1: 10497 | NH1: 10498 | NI1: 10500
A2: Customer ID | B2: 1102 | C2: 1435 | D2: 1860 | E2: 1270 | F2: 1106 | G2: 1071 | H2: 1700 | I2: 1020 | J2: 1614 | K2: 1121 | L2: 1466 | M2: 1214 | N2: 1330 | O2: 1458 | P2: 1087 | Q2: 1372 | R2: 1099 | S2: 1871 | T2: 1663 | U2: 1130 | V2: 1661 | W2: 1308 | X2: 1769 | Y2: 1343 | Z2: 1491 | AA2: 1413 | AB2: 1805 | AC2: 1385 | AD2: 1191 | AE2: 1955 | AF2: 1276 | AG2: 1160 | AH2: 1459 | AI2: 1313 | AJ2: 1021 | AK2: 1252 | AL2: 1747 | AM2: 1856 | AN2: 1560 | AO2: 1474 | AP2: 1058 | AQ2: 1510 | AR2: 1681 | AS2: 1475 | AT2: 1699 | AU2: 1975 | AV2: 1782 | AW2: 1189 | AX2: 1957 | AY2: 1686 | AZ2: 1562 | BA2: 1875 | BB2: 1566 | BC2: 1243 | BD2: 1831 | BE2: 1504 | BF2: 1484 | BG2: 1818 | BH2: 1646 | BI2: 1840 | BJ2: 1166 | BK2: 1273 | BL2: 1387 | BM2: 1600 | BN2: 1315 | BO2: 1013 | BP2: 1241 | BQ2: 1776 | BR2: 1345 | BS2: 1564 | BT2: 1897 | BU2: 1339 | BV2: 1091 | BW2: 1366 | BX2: 1454 | BY2: 1427 | BZ2: 1508 | CA2: 1775 | CB2: 1942 | CC2: 1034 | CD2: 1205 | CE2: 1080 | CF2: 1931 | CG2: 1561 | CH2: 1001 | CI2: 1389 | CJ2: 1565 | CK2: 1105 | CL2: 1771 | CM2: 1821 | CN2: 1476 | CO2: 1702 | CP2: 1401 | CQ2: 1729 | CR2: 1555 | CS2: 1161 | CT2: 1201 | CU2: 1995 | CV2: 1269 | CW2: 1862 | CX2: 1815 | CY2: 1455 | CZ2: 1461 | DA2: 1726 | DB2: 1251 | DC2: 1701 | DD2: 1295 | DE2: 1724 | DF2: 1719 | DG2: 1748 | DH2: 1337 | DI2: 1878 | DJ2: 1052 | DK2: 1791 | DL2: 1921 | DM2: 1216 | DN2: 1763 | DO2: 1187 | DP2: 1379 | DQ2: 1492 | DR2: 1040 | DS2: 1156 | DT2: 1014 | DU2: 1812 | DV2: 1064 | DW2: 1838 | DX2: 1520 | DY2: 1128 | DZ2: 1647 | EA2: 1471 | EB2: 1062 | EC2: 1138 | ED2: 1498 | EE2: 1592 | EF2: 1391 | EG2: 1674 | EH2: 1418 | EI2: 1288 | EJ2: 1378 | EK2: 1772 | EL2: 1489 | EM2: 1230 | EN2: 1027 | EO2: 1134 | EP2: 1200 | EQ2: 1839 | ER2: 1779 | ES2: 1929 | ET2: 1032 | EU2: 1047 | EV2: 1502 | EW2: 1406 | EX2: 1573 | EY2: 1727 | EZ2: 1804 | FA2: 1098 | FB2: 1683 | FC2: 1725 | FD2: 1986 | FE2: 1546 | FF2: 1960 | FG2: 1738 | FH2: 1612 | FI2: 1642 | FJ2: 1768 | FK2: 1004 | FL2: 1217 | FM2: 1766 | FN2: 1397 | FO2: 1870 | FP2: 1794 | FQ2: 1392 | FR2: 1206 | FS2: 1857 | FT2: 1553 | FU2: 1891 | FV2: 1460 | FW2: 1690 | FX2: 1574 | FY2: 1863 | FZ2: 1742 | GA2: 1240 | GB2: 1563 | GC2: 1095 | GD2: 1899 | GE2: 1733 | GF2: 1654 | GG2: 1170 | GH2: 1540 | GI2: 1035 | GJ2: 1524 | GK2: 1159 | GL2: 1698 | GM2: 1242 | GN2: 1085 | GO2: 1795 | GP2: 1577 | GQ2: 1556 | GR2: 1952 | GS2: 1645 | GT2: 1619 | GU2: 1797 | GV2: 1639 | GW2: 1505 | GX2: 1347 | GY2: 1472 | GZ2: 1224 | HA2: 1384 | HB2: 1376 | HC2: 1282 | HD2: 1632 | HE2: 1627 | HF2: 1972 | HG2: 1744 | HH2: 1258 | HI2: 1358 | HJ2: 1709 | HK2: 1410 | HL2: 1648 | HM2: 1317 | HN2: 1676 | HO2: 1233 | HP2: 1974 | HQ2: 1826 | HR2: 1373 | HS2: 1671 | HT2: 1607 | HU2: 1232 | HV2: 1691 | HW2: 1112 | HX2: 1829 | HY2: 1496 | HZ2: 1441 | IA2: 1267 | IB2: 1509 | IC2: 1806 | ID2: 1386 | IE2: 1624 | IF2: 1951 | IG2: 1641 | IH2: 1219 | II2: 1854 | IJ2: 1996 | IK2: 1735 | IL2: 1402 | IM2: 1637 | IN2: 1129 | IO2: 1415 | IP2: 1246 | IQ2: 1835 | IR2: 1438 | IS2: 1202 | IT2: 1183 | IU2: 1122 | IV2: 1400 | IW2: 1293 | IX2: 1279 | IY2: 1836 | IZ2: 1883 | JA2: 1609 | JB2: 1197 | JC2: 1981 | JD2: 1906 | JE2: 1751 | JF2: 1143 | JG2: 1608 | JH2: 1123 | JI2: 1186 | JJ2: 1325 | JK2: 1463 | JL2: 1348 | JM2: 1770 | JN2: 1659 | JO2: 1954 | JP2: 1962 | JQ2: 1146 | JR2: 1147 | JS2: 1710 | JT2: 1819 | JU2: 1488 | JV2: 1928 | JW2: 1935 | JX2: 1550 | JY2: 1640 | JZ2: 1778 | KA2: 1987 | KB2: 1945 | KC2: 1150 | KD2: 1414 | KE2: 1989 | KF2: 1297 | KG2: 1610 | KH2: 1262 | KI2: 1623 | KJ2: 1571 | KK2: 1880 | KL2: 1896 | KM2: 1303 | KN2: 1253 | KO2: 1651 | KP2: 1452 | KQ2: 1036 | KR2: 1008 | KS2: 1658 | KT2: 1207 | KU2: 1403 | KV2: 1151 | KW2: 1053 | KX2: 1119 | KY2: 1672 | KZ2: 1919 | LA2: 1586 | LB2: 1967 | LC2: 1419 | LD2: 1421 | LE2: 1103 | LF2: 1851 | LG2: 1226 | LH2: 1111 | LI2: 1152 | LJ2: 1913 | LK2: 1895 | LL2: 1877 | LM2: 1705 | LN2: 1162 | LO2: 1956 | LP2: 1680 | LQ2: 1579 | LR2: 1800 | LS2: 1915 | LT2: 1503 | LU2: 1194 | LV2: 1687 | LW2: 1882 | LX2: 1469 | LY2: 1374 | LZ2: 1749 | MA2: 1669 | MB2: 1037 | MC2: 1229 | MD2: 1364 | ME2: 1437 | MF2: 1026 | MG2: 1225 | MH2: 1283 | MI2: 1959 | MJ2: 1480 | MK2: 1828 | ML2: 1515 | MM2: 1048 | MN2: 1511 | MO2: 1016 | MP2: 1171 | MQ2: 1157 | MR2: 1045 | MS2: 1517 | MT2: 1301 | MU2: 1180 | MV2: 1606 | MW2: 1992 | MX2: 1115 | MY2: 1190 | MZ2: 1980 | NA2: 1927 | NB2: 1982 | NC2: 1255 | ND2: 1322 | NE2: 1127 | NF2: 1017 | NG2: 1792 | NH2: 1734 | NI2: 1569
A3: Order Date | B3: 45197 | C3: 45199 | D3: 45109 | E3: 45079 | F3: 45241 | G3: 45260 | H3: 45050 | I3: 45040 | J3: 45204 | K3: 45139 | L3: 45098 | M3: 45214 | N3: 45100 | O3: 45039 | P3: 45048 | Q3: 44958 | R3: 45148 | S3: 45045 | T3: 44965 | U3: 45194 | V3: 45159 | W3: 44944 | X3: 45075 | Y3: 45075 | Z3: 45052 | AA3: 45228 | AB3: 45286 | AC3: 45164 | AD3: 45061 | AE3: 45077 | AF3: 45162 | AG3: 45150 | AH3: 45129 | AI3: 45182 | AJ3: 45012 | AK3: 45076 | AL3: 45161 | AM3: 45271 | AN3: 44948 | AO3: 45274 | AP3: 45211 | AQ3: 45195 | AR3: 45184 | AS3: 44955 | AT3: 45139 | AU3: 45209 | AV3: 44976 | AW3: 45021 | AX3: 45014 | AY3: 44970 | AZ3: 45097 | BA3: 45115 | BB3: 45279 | BC3: 45110 | BD3: 44929 | BE3: 45117 | BF3: 44945 | BG3: 44949 | BH3: 44956 | BI3: 45034 | BJ3: 45207 | BK3: 45054 | BL3: 45155 | BM3: 45037 | BN3: 45062 | BO3: 45288 | BP3: 45112 | BQ3: 45070 | BR3: 44998 | BS3: 45055 | BT3: 45290 | BU3: 45187 | BV3: 44929 | BW3: 45030 | BX3: 45246 | BY3: 45288 | BZ3: 45280 | CA3: 44936 | CB3: 45228 | CC3: 45157 | CD3: 45145 | CE3: 44992 | CF3: 45038 | CG3: 44939 | CH3: 45016 | CI3: 45240 | CJ3: 44980 | CK3: 44938 | CL3: 45135 | CM3: 44940 | CN3: 45047 | CO3: 44946 | CP3: 45001 | CQ3: 45169 | CR3: 45149 | CS3: 44996 | CT3: 45238 | CU3: 45027 | CV3: 45112 | CW3: 45058 | CX3: 45037 | CY3: 44946 | CZ3: 44950 | DA3: 45153 | DB3: 45080 | DC3: 45219 | DD3: 45156 | DE3: 45236 | DF3: 45285 | DG3: 45128 | DH3: 44964 | DI3: 45186 | DJ3: 45114 | DK3: 44983 | DL3: 44946 | DM3: 45199 | DN3: 45045 | DO3: 44997 | DP3: 44930 | DQ3: 45147 | DR3: 44940 | DS3: 44929 | DT3: 45142 | DU3: 45155 | DV3: 45262 | DW3: 44981 | DX3: 45180 | DY3: 45088 | DZ3: 45084 | EA3: 45008 | EB3: 45085 | EC3: 45114 | ED3: 44986 | EE3: 45231 | EF3: 45245 | EG3: 45137 | EH3: 45078 | EI3: 45035 | EJ3: 45002 | EK3: 44956 | EL3: 45240 | EM3: 45043 | EN3: 45118 | EO3: 44945 | EP3: 45099 | EQ3: 45154 | ER3: 45276 | ES3: 45109 | ET3: 45039 | EU3: 45109 | EV3: 45072 | EW3: 45245 | EX3: 45042 | EY3: 45039 | EZ3: 45177 | FA3: 45177 | FB3: 45229 | FC3: 45044 | FD3: 45227 | FE3: 45087 | FF3: 45124 | FG3: 45186 | FH3: 45074 | FI3: 45124 | FJ3: 44973 | FK3: 45004 | FL3: 45050 | FM3: 45285 | FN3: 45063 | FO3: 45016 | FP3: 45251 | FQ3: 44987 | FR3: 45064 | FS3: 45185 | FT3: 45033 | FU3: 45039 | FV3: 45276 | FW3: 45180 | FX3: 45044 | FY3: 45124 | FZ3: 45263 | GA3: 45291 | GB3: 44977 | GC3: 45171 | GD3: 44961 | GE3: 45228 | GF3: 45000 | GG3: 45118 | GH3: 45187 | GI3: 45282 | GJ3: 44996 | GK3: 45016 | GL3: 45052 | GM3: 45157 | GN3: 45221 | GO3: 45055 | GP3: 45206 | GQ3: 45026 | GR3: 45223 | GS3: 45108 | GT3: 45290 | GU3: 44957 | GV3: 44962 | GW3: 45139 | GX3: 45290 | GY3: 45032 | GZ3: 45089 | HA3: 45146 | HB3: 45196 | HC3: 45046 | HD3: 45108 | HE3: 45032 | HF3: 45143 | HG3: 45131 | HH3: 44996 | HI3: 44970 | HJ3: 45255 | HK3: 45154 | HL3: 45110 | HM3: 45033 | HN3: 45010 | HO3: 45289 | HP3: 45104 | HQ3: 44933 | HR3: 44996 | HS3: 45053 | HT3: 45086 | HU3: 45129 | HV3: 45074 | HW3: 45069 | HX3: 45125 | HY3: 45080 | HZ3: 45068 | IA3: 45091 | IB3: 45240 | IC3: 44947 | ID3: 44995 | IE3: 45144 | IF3: 45231 | IG3: 45043 | IH3: 45122 | II3: 45012 | IJ3: 45215 | IK3: 45007 | IL3: 44987 | IM3: 45280 | IN3: 44954 | IO3: 45024 | IP3: 45124 | IQ3: 45024 | IR3: 44991 | IS3: 45256 | IT3: 45267 | IU3: 44931 | IV3: 44928 | IW3: 45038 | IX3: 44983 | IY3: 44992 | IZ3: 45256 | JA3: 45024 | JB3: 45070 | JC3: 45051 | JD3: 45093 | JE3: 45002 | JF3: 45270 | JG3: 45220 | JH3: 45064 | JI3: 45025 | JJ3: 45118 | JK3: 45169 | JL3: 45245 | JM3: 44975 | JN3: 44958 | JO3: 44946 | JP3: 45069 | JQ3: 45139 | JR3: 45005 | JS3: 45042 | JT3: 45018 | JU3: 45196 | JV3: 45094 | JW3: 44984 | JX3: 44952 | JY3: 45180 | JZ3: 44970 | KA3: 45023 | KB3: 45188 | KC3: 45093 | KD3: 45205 | KE3: 45015 | KF3: 45104 | KG3: 45123 | KH3: 45233 | KI3: 44934 | KJ3: 45223 | KK3: 45090 | KL3: 44998 | KM3: 44981 | KN3: 44973 | KO3: 45164 | KP3: 45030 | KQ3: 45136 | KR3: 45242 | KS3: 45262 | KT3: 45185 | KU3: 45040 | KV3: 45289 | KW3: 44966 | KX3: 45146 | KY3: 45055 | KZ3: 44934 | LA3: 45102 | LB3: 45027 | LC3: 45186 | LD3: 45172 | LE3: 45201 | LF3: 44958 | LG3: 44938 | LH3: 45228 | LI3: 45035 | LJ3: 45084 | LK3: 45195 | LL3: 45088 | LM3: 45028 | LN3: 44985 | LO3: 45054 | LP3: 45209 | LQ3: 45057 | LR3: 45279 | LS3: 45059 | LT3: 45153 | LU3: 45137 | LV3: 45139 | LW3: 45057 | LX3: 45002 | LY3: 45212 | LZ3: 45082 | MA3: 45174 | MB3: 45144 | MC3: 45116 | MD3: 45089 | ME3: 44960 | MF3: 45264 | MG3: 45240 | MH3: 45076 | MI3: 45251 | MJ3: 45034 | MK3: 45276 | ML3: 45215 | MM3: 44992 | MN3: 45174 | MO3: 45082 | MP3: 44973 | MQ3: 45074 | MR3: 44927 | MS3: 45269 | MT3: 45117 | MU3: 44947 | MV3: 45153 | MW3: 45228 | MX3: 45068 | MY3: 44965 | MZ3: 45178 | NA3: 45259 | NB3: 45133 | NC3: 45041 | ND3: 45151 | NE3: 45060 | NF3: 45177 | NG3: 45145 | NH3: 45017 | NI3: 44972
A4: Ship Date | B4: 45203 | C4: 45203 | D4: 45114 | E4: 45087 | F4: 45244 | G4: 45263 | H4: 45054 | I4: 45041 | J4: 45213 | K4: 45147 | L4: 45106 | M4: 45220 | N4: 45107 | O4: 45045 | P4: 45057 | Q4: 44961 | R4: 45151 | S4: 45048 | T4: 44968 | U4: 45203 | V4: 45163 | W4: 44951 | X4: 45084 | Y4: 45082 | Z4: 45061 | AA4: 45231 | AB4: 45290 | AC4: 45172 | AD4: 45067 | AE4: 45082 | AF4: 45166 | AG4: 45158 | AH4: 45130 | AI4: 45191 | AJ4: 45013 | AK4: 45084 | AL4: 45165 | AM4: 45280 | AN4: 44953 | AO4: 45277 | AP4: 45220 | AQ4: 45204 | AR4: 45188 | AS4: 44959 | AT4: 45147 | AU4: 45211 | AV4: 44985 | AW4: 45027 | AX4: 45023 | AY4: 44978 | AZ4: 45098 | BA4: 45118 | BB4: 45281 | BC4: 45115 | BD4: 44934 | BE4: 45122 | BF4: 44950 | BG4: 44952 | BH4: 44957 | BI4: 45043 | BJ4: 45216 | BK4: 45058 | BL4: 45158 | BM4: 45038 | BN4: 45064 | BO4: 45296 | BP4: 45113 | BQ4: 45078 | BR4: 45005 | BS4: 45063 | BT4: 45296 | BU4: 45196 | BV4: 44932 | BW4: 45034 | BX4: 45254 | BY4: 45293 | BZ4: 45283 | CA4: 44942 | CB4: 45232 | CC4: 45166 | CD4: 45148 | CE4: 44996 | CF4: 45045 | CG4: 44946 | CH4: 45019 | CI4: 45246 | CJ4: 44982 | CK4: 44946 | CL4: 45137 | CM4: 44947 | CN4: 45056 | CO4: 44947 | CP4: 45009 | CQ4: 45176 | CR4: 45155 | CS4: 45002 | CT4: 45244 | CU4: 45029 | CV4: 45113 | CW4: 45064 | CX4: 45045 | CY4: 44947 | CZ4: 44959 | DA4: 45154 | DB4: 45083 | DC4: 45227 | DD4: 45159 | DE4: 45240 | DF4: 45293 | DG4: 45129 | DH4: 44970 | DI4: 45187 | DJ4: 45115 | DK4: 44991 | DL4: 44950 | DM4: 45200 | DN4: 45052 | DO4: 45002 | DP4: 44935 | DQ4: 45148 | DR4: 44946 | DS4: 44938 | DT4: 45151 | DU4: 45163 | DV4: 45267 | DW4: 44990 | DX4: 45181 | DY4: 45093 | DZ4: 45087 | EA4: 45015 | EB4: 45092 | EC4: 45123 | ED4: 44993 | EE4: 45234 | EF4: 45246 | EG4: 45145 | EH4: 45081 | EI4: 45043 | EJ4: 45010 | EK4: 44961 | EL4: 45241 | EM4: 45050 | EN4: 45126 | EO4: 44954 | EP4: 45106 | EQ4: 45161 | ER4: 45277 | ES4: 45113 | ET4: 45041 | EU4: 45111 | EV4: 45074 | EW4: 45249 | EX4: 45043 | EY4: 45043 | EZ4: 45179 | FA4: 45182 | FB4: 45232 | FC4: 45048 | FD4: 45228 | FE4: 45088 | FF4: 45127 | FG4: 45195 | FH4: 45081 | FI4: 45126 | FJ4: 44976 | FK4: 45006 | FL4: 45053 | FM4: 45294 | FN4: 45072 | FO4: 45023 | FP4: 45254 | FQ4: 44991 | FR4: 45070 | FS4: 45187 | FT4: 45039 | FU4: 45042 | FV4: 45284 | FW4: 45182 | FX4: 45045 | FY4: 45133 | FZ4: 45266 | GA4: 45292 | GB4: 44984 | GC4: 45176 | GD4: 44966 | GE4: 45229 | GF4: 45006 | GG4: 45123 | GH4: 45193 | GI4: 45284 | GJ4: 45000 | GK4: 45019 | GL4: 45061 | GM4: 45162 | GN4: 45227 | GO4: 45057 | GP4: 45209 | GQ4: 45035 | GR4: 45231 | GS4: 45117 | GT4: 45291 | GU4: 44959 | GV4: 44969 | GW4: 45143 | GX4: 45295 | GY4: 45040 | GZ4: 45093 | HA4: 45149 | HB4: 45198 | HC4: 45049 | HD4: 45109 | HE4: 45038 | HF4: 45148 | HG4: 45139 | HH4: 44998 | HI4: 44974 | HJ4: 45263 | HK4: 45155 | HL4: 45114 | HM4: 45034 | HN4: 45012 | HO4: 45297 | HP4: 45110 | HQ4: 44936 | HR4: 44998 | HS4: 45059 | HT4: 45091 | HU4: 45134 | HV4: 45079 | HW4: 45072 | HX4: 45132 | HY4: 45086 | HZ4: 45072 | IA4: 45100 | IB4: 45241 | IC4: 44951 | ID4: 45001 | IE4: 45149 | IF4: 45240 | IG4: 45050 | IH4: 45125 | II4: 45014 | IJ4: 45218 | IK4: 45008 | IL4: 44994 | IM4: 45284 | IN4: 44957 | IO4: 45027 | IP4: 45125 | IQ4: 45027 | IR4: 44993 | IS4: 45264 | IT4: 45273 | IU4: 44940 | IV4: 44936 | IW4: 45043 | IX4: 44990 | IY4: 44997 | IZ4: 45264 | JA4: 45029 | JB4: 45071 | JC4: 45056 | JD4: 45097 | JE4: 45005 | JF4: 45275 | JG4: 45222 | JH4: 45070 | JI4: 45030 | JJ4: 45124 | JK4: 45176 | JL4: 45250 | JM4: 44976 | JN4: 44966 | JO4: 44955 | JP4: 45072 | JQ4: 45145 | JR4: 45012 | JS4: 45048 | JT4: 45019 | JU4: 45204 | JV4: 45101 | JW4: 44993 | JX4: 44954 | JY4: 45185 | JZ4: 44972 | KA4: 45026 | KB4: 45191 | KC4: 45102 | KD4: 45213 | KE4: 45019 | KF4: 45105 | KG4: 45124 | KH4: 45234 | KI4: 44940 | KJ4: 45226 | KK4: 45095 | KL4: 45000 | KM4: 44987 | KN4: 44979 | KO4: 45167 | KP4: 45036 | KQ4: 45141 | KR4: 45251 | KS4: 45270 | KT4: 45188 | KU4: 45042 | KV4: 45297 | KW4: 44967 | KX4: 45154 | KY4: 45062 | KZ4: 44941 | LA4: 45103 | LB4: 45036 | LC4: 45191 | LD4: 45173 | LE4: 45206 | LF4: 44966 | LG4: 44943 | LH4: 45237 | LI4: 45037 | LJ4: 45091 | LK4: 45204 | LL4: 45090 | LM4: 45034 | LN4: 44993 | LO4: 45056 | LP4: 45212 | LQ4: 45065 | LR4: 45280 | LS4: 45061 | LT4: 45155 | LU4: 45140 | LV4: 45146 | LW4: 45062 | LX4: 45009 | LY4: 45213 | LZ4: 45091 | MA4: 45179 | MB4: 45149 | MC4: 45119 | MD4: 45094 | ME4: 44969 | MF4: 45265 | MG4: 45247 | MH4: 45082 | MI4: 45255 | MJ4: 45036 | MK4: 45280 | ML4: 45221 | MM4: 45000 | MN4: 45176 | MO4: 45089 | MP4: 44975 | MQ4: 45082 | MR4: 44936 | MS4: 45278 | MT4: 45119 | MU4: 44955 | MV4: 45162 | MW4: 45237 | MX4: 45077 | MY4: 44966 | MZ4: 45187 | NA4: 45261 | NB4: 45137 | NC4: 45043 | ND4: 45154 | NE4: 45063 | NF4: 45178 | NG4: 45151 | NH4: 45025 | NI4: 44977
A5: City | B5: Chennai | C5: Pune | D5: Chennai | E5: Bengaluru | F5: Kolkata | G5: Hyderabad | H5: Bengaluru | I5: Mumbai | J5: Chennai | K5: Bengaluru | L5: Bengaluru | M5: Mumbai | N5: Delhi | O5: Kolkata | P5: Hyderabad | Q5: Pune | R5: Delhi | S5: Chennai | T5: Bengaluru | U5: Mumbai | V5: Mumbai | W5: Kolkata | X5: Delhi | Y5: Pune | Z5: Kolkata | AA5: Bengaluru | AB5: Kolkata | AC5: Hyderabad | AD5: Mumbai | AE5: Mumbai | AF5: Chennai | AG5: Chennai | AH5: Pune | AI5: Bengaluru | AJ5: Hyderabad | AK5: Delhi | AL5: Kolkata | AM5: Pune | AN5: Bengaluru | AO5: Chennai | AP5: Kolkata | AQ5: Chennai | AR5: Kolkata | AS5: Delhi | AT5: Bengaluru | AU5: Kolkata | AV5: Hyderabad | AW5: Pune | AX5: Mumbai | AY5: Hyderabad | AZ5: Pune | BA5: Mumbai | BB5: Hyderabad | BC5: Kolkata | BD5: Kolkata | BE5: Kolkata | BF5: Hyderabad | BG5: Mumbai | BH5: Kolkata | BI5: Hyderabad | BJ5: Hyderabad | BK5: Chennai | BL5: Chennai | BM5: Delhi | BN5: Bengaluru | BO5: Chennai | BP5: Mumbai | BQ5: Chennai | BR5: Delhi | BS5: Hyderabad | BT5: Delhi | BU5: Hyderabad | BV5: Pune | BW5: Pune | BX5: Bengaluru | BY5: Chennai | BZ5: Mumbai | CA5: Mumbai | CB5: Kolkata | CC5: Hyderabad | CD5: Mumbai | CE5: Bengaluru | CF5: Hyderabad | CG5: Bengaluru | CH5: Kolkata | CI5: Mumbai | CJ5: Hyderabad | CK5: Pune | CL5: Hyderabad | CM5: Hyderabad | CN5: Kolkata | CO5: Kolkata | CP5: Mumbai | CQ5: Delhi | CR5: Delhi | CS5: Kolkata | CT5: Mumbai | CU5: Mumbai | CV5: Mumbai | CW5: Mumbai | CX5: Chennai | CY5: Mumbai | CZ5: Chennai | DA5: Kolkata | DB5: Delhi | DC5: Hyderabad | DD5: Pune | DE5: Delhi | DF5: Hyderabad | DG5: Pune | DH5: Delhi | DI5: Hyderabad | DJ5: Delhi | DK5: Delhi | DL5: Pune | DM5: Delhi | DN5: Delhi | DO5: Pune | DP5: Kolkata | DQ5: Mumbai | DR5: Bengaluru | DS5: Chennai | DT5: Bengaluru | DU5: Bengaluru | DV5: Hyderabad | DW5: Hyderabad | DX5: Mumbai | DY5: Pune | DZ5: Mumbai | EA5: Delhi | EB5: Kolkata | EC5: Delhi | ED5: Kolkata | EE5: Hyderabad | EF5: Kolkata | EG5: Hyderabad | EH5: Pune | EI5: Bengaluru | EJ5: Pune | EK5: Pune | EL5: Bengaluru | EM5: Kolkata | EN5: Hyderabad | EO5: Delhi | EP5: Hyderabad | EQ5: Delhi | ER5: Pune | ES5: Bengaluru | ET5: Pune | EU5: Mumbai | EV5: Kolkata | EW5: Delhi | EX5: Hyderabad | EY5: Bengaluru | EZ5: Delhi | FA5: Hyderabad | FB5: Kolkata | FC5: Kolkata | FD5: Chennai | FE5: Mumbai | FF5: Chennai | FG5: Bengaluru | FH5: Delhi | FI5: Hyderabad | FJ5: Kolkata | FK5: Chennai | FL5: Chennai | FM5: Chennai | FN5: Pune | FO5: Bengaluru | FP5: Kolkata | FQ5: Delhi | FR5: Hyderabad | FS5: Bengaluru | FT5: Hyderabad | FU5: Chennai | FV5: Mumbai | FW5: Bengaluru | FX5: Bengaluru | FY5: Kolkata | FZ5: Delhi | GA5: Bengaluru | GB5: Bengaluru | GC5: Chennai | GD5: Chennai | GE5: Hyderabad | GF5: Kolkata | GG5: Mumbai | GH5: Hyderabad | GI5: Chennai | GJ5: Pune | GK5: Delhi | GL5: Kolkata | GM5: Chennai | GN5: Kolkata | GO5: Kolkata | GP5: Kolkata | GQ5: Kolkata | GR5: Delhi | GS5: Mumbai | GT5: Kolkata | GU5: Delhi | GV5: Pune | GW5: Delhi | GX5: Kolkata | GY5: Hyderabad | GZ5: Bengaluru | HA5: Bengaluru | HB5: Delhi | HC5: Hyderabad | HD5: Kolkata | HE5: Bengaluru | HF5: Chennai | HG5: Delhi | HH5: Chennai | HI5: Pune | HJ5: Mumbai | HK5: Delhi | HL5: Kolkata | HM5: Hyderabad | HN5: Pune | HO5: Hyderabad | HP5: Pune | HQ5: Chennai | HR5: Chennai | HS5: Hyderabad | HT5: Chennai | HU5: Hyderabad | HV5: Hyderabad | HW5: Kolkata | HX5: Chennai | HY5: Pune | HZ5: Hyderabad | IA5: Mumbai | IB5: Kolkata | IC5: Delhi | ID5: Hyderabad | IE5: Mumbai | IF5: Mumbai | IG5: Chennai | IH5: Pune | II5: Kolkata | IJ5: Kolkata | IK5: Chennai | IL5: Pune | IM5: Bengaluru | IN5: Delhi | IO5: Delhi | IP5: Kolkata | IQ5: Hyderabad | IR5: Mumbai | IS5: Mumbai | IT5: Chennai | IU5: Kolkata | IV5: Bengaluru | IW5: Mumbai | IX5: Mumbai | IY5: Hyderabad | IZ5: Kolkata | JA5: Kolkata | JB5: Mumbai | JC5: Bengaluru | JD5: Chennai | JE5: Chennai | JF5: Kolkata | JG5: Chennai | JH5: Mumbai | JI5: Kolkata | JJ5: Kolkata | JK5: Pune | JL5: Pune | JM5: Hyderabad | JN5: Kolkata | JO5: Chennai | JP5: Delhi | JQ5: Pune | JR5: Chennai | JS5: Delhi | JT5: Chennai | JU5: Mumbai | JV5: Pune | JW5: Bengaluru | JX5: Chennai | JY5: Chennai | JZ5: Mumbai | KA5: Mumbai | KB5: Kolkata | KC5: Delhi | KD5: Kolkata | KE5: Chennai | KF5: Delhi | KG5: Bengaluru | KH5: Bengaluru | KI5: Delhi | KJ5: Chennai | KK5: Mumbai | KL5: Pune | KM5: Pune | KN5: Bengaluru | KO5: Delhi | KP5: Pune | KQ5: Kolkata | KR5: Kolkata | KS5: Chennai | KT5: Delhi | KU5: Kolkata | KV5: Pune | KW5: Delhi | KX5: Chennai | KY5: Mumbai | KZ5: Pune | LA5: Hyderabad | LB5: Pune | LC5: Hyderabad | LD5: Pune | LE5: Delhi | LF5: Mumbai | LG5: Pune | LH5: Delhi | LI5: Delhi | LJ5: Mumbai | LK5: Delhi | LL5: Pune | LM5: Kolkata | LN5: Mumbai | LO5: Kolkata | LP5: Mumbai | LQ5: Pune | LR5: Hyderabad | LS5: Delhi | LT5: Hyderabad | LU5: Hyderabad | LV5: Mumbai | LW5: Mumbai | LX5: Chennai | LY5: Chennai | LZ5: Mumbai | MA5: Bengaluru | MB5: Kolkata | MC5: Delhi | MD5: Chennai | ME5: Hyderabad | MF5: Bengaluru | MG5: Hyderabad | MH5: Mumbai | MI5: Bengaluru | MJ5: Chennai | MK5: Mumbai | ML5: Pune | MM5: Pune | MN5: Mumbai | MO5: Kolkata | MP5: Delhi | MQ5: Pune | MR5: Bengaluru | MS5: Chennai | MT5: Delhi | MU5: Bengaluru | MV5: Bengaluru | MW5: Delhi | MX5: Delhi | MY5: Hyderabad | MZ5: Bengaluru | NA5: Chennai | NB5: Delhi | NC5: Hyderabad | ND5: Kolkata | NE5: Chennai | NF5: Chennai | NG5: Delhi | NH5: Mumbai | NI5: Chennai
A6: State | B6: Delhi | C6: Tamil Nadu | D6: West Bengal | E6: West Bengal | F6: Karnataka | G6: Telangana | H6: Telangana | I6: Delhi | J6: West Bengal | K6: Karnataka | L6: Karnataka | M6: Tamil Nadu | N6: Tamil Nadu | O6: Karnataka | P6: Tamil Nadu | Q6: West Bengal | R6: Maharashtra | S6: West Bengal | T6: Karnataka | U6: Karnataka | V6: West Bengal | W6: Tamil Nadu | X6: Tamil Nadu | Y6: Telangana | Z6: Karnataka | AA6: Delhi | AB6: Telangana | AC6: Tamil Nadu | AD6: West Bengal | AE6: Tamil Nadu | AF6: West Bengal | AG6: Telangana | AH6: Karnataka | AI6: Tamil Nadu | AJ6: West Bengal | AK6: Karnataka | AL6: Delhi | AM6: West Bengal | AN6: Telangana | AO6: Delhi | AP6: Delhi | AQ6: Maharashtra | AR6: Tamil Nadu | AS6: West Bengal | AT6: Delhi | AU6: Maharashtra | AV6: Telangana | AW6: Karnataka | AX6: West Bengal | AY6: Delhi | AZ6: Maharashtra | BA6: Delhi | BB6: Tamil Nadu | BC6: Delhi | BD6: West Bengal | BE6: West Bengal | BF6: Telangana | BG6: Telangana | BH6: Maharashtra | BI6: Tamil Nadu | BJ6: Delhi | BK6: Karnataka | BL6: Tamil Nadu | BM6: Telangana | BN6: Telangana | BO6: Tamil Nadu | BP6: Telangana | BQ6: West Bengal | BR6: Maharashtra | BS6: Delhi | BT6: Maharashtra | BU6: Delhi | BV6: Delhi | BW6: Maharashtra | BX6: Delhi | BY6: Maharashtra | BZ6: Delhi | CA6: Karnataka | CB6: Tamil Nadu | CC6: West Bengal | CD6: Delhi | CE6: Karnataka | CF6: West Bengal | CG6: West Bengal | CH6: Delhi | CI6: Karnataka | CJ6: West Bengal | CK6: Delhi | CL6: Maharashtra | CM6: Delhi | CN6: Tamil Nadu | CO6: Maharashtra | CP6: Karnataka | CQ6: West Bengal | CR6: Delhi | CS6: Maharashtra | CT6: Tamil Nadu | CU6: Telangana | CV6: Tamil Nadu | CW6: Karnataka | CX6: West Bengal | CY6: Delhi | CZ6: Maharashtra | DA6: Telangana | DB6: Tamil Nadu | DC6: Tamil Nadu | DD6: Maharashtra | DE6: Telangana | DF6: Maharashtra | DG6: Delhi | DH6: Karnataka | DI6: Tamil Nadu | DJ6: Delhi | DK6: Karnataka | DL6: Delhi | DM6: Telangana | DN6: Tamil Nadu | DO6: Maharashtra | DP6: Maharashtra | DQ6: Karnataka | DR6: West Bengal | DS6: Telangana | DT6: Karnataka | DU6: West Bengal | DV6: Delhi | DW6: Delhi | DX6: Tamil Nadu | DY6: West Bengal | DZ6: Tamil Nadu | EA6: Maharashtra | EB6: West Bengal | EC6: Karnataka | ED6: Maharashtra | EE6: Maharashtra | EF6: Karnataka | EG6: Telangana | EH6: Maharashtra | EI6: West Bengal | EJ6: Tamil Nadu | EK6: Maharashtra | EL6: West Bengal | EM6: Delhi | EN6: Tamil Nadu | EO6: West Bengal | EP6: Karnataka | EQ6: Tamil Nadu | ER6: Telangana | ES6: Delhi | ET6: Karnataka | EU6: Telangana | EV6: West Bengal | EW6: Tamil Nadu | EX6: Delhi | EY6: Karnataka | EZ6: Telangana | FA6: Telangana | FB6: Delhi | FC6: Delhi | FD6: Telangana | FE6: Maharashtra | FF6: Karnataka | FG6: Delhi | FH6: Telangana | FI6: West Bengal | FJ6: Delhi | FK6: West Bengal | FL6: Tamil Nadu | FM6: Tamil Nadu | FN6: Maharashtra | FO6: Delhi | FP6: Telangana | FQ6: Telangana | FR6: Maharashtra | FS6: Maharashtra | FT6: West Bengal | FU6: West Bengal | FV6: Karnataka | FW6: Telangana | FX6: Tamil Nadu | FY6: West Bengal | FZ6: Karnataka | GA6: Telangana | GB6: Tamil Nadu | GC6: West Bengal | GD6: West Bengal | GE6: Maharashtra | GF6: Telangana | GG6: Telangana | GH6: Delhi | GI6: Maharashtra | GJ6: Tamil Nadu | GK6: West Bengal | GL6: West Bengal | GM6: Delhi | GN6: Tamil Nadu | GO6: Telangana | GP6: West Bengal | GQ6: Delhi | GR6: Delhi | GS6: Maharashtra | GT6: Karnataka | GU6: Maharashtra | GV6: West Bengal | GW6: Telangana | GX6: Delhi | GY6: West Bengal | GZ6: Karnataka | HA6: Telangana | HB6: Karnataka | HC6: Telangana | HD6: Tamil Nadu | HE6: West Bengal | HF6: Delhi | HG6: West Bengal | HH6: Maharashtra | HI6: Delhi | HJ6: Telangana | HK6: Tamil Nadu | HL6: Karnataka | HM6: Telangana | HN6: Delhi | HO6: Telangana | HP6: Telangana | HQ6: Maharashtra | HR6: Tamil Nadu | HS6: Karnataka | HT6: Delhi | HU6: Delhi | HV6: Karnataka | HW6: Delhi | HX6: Telangana | HY6: West Bengal | HZ6: Delhi | IA6: Maharashtra | IB6: Delhi | IC6: Maharashtra | ID6: Telangana | IE6: Telangana | IF6: Maharashtra | IG6: West Bengal | IH6: Karnataka | II6: Maharashtra | IJ6: Telangana | IK6: Maharashtra | IL6: Delhi | IM6: Tamil Nadu | IN6: Delhi | IO6: West Bengal | IP6: West Bengal | IQ6: Tamil Nadu | IR6: Telangana | IS6: West Bengal | IT6: Delhi | IU6: Tamil Nadu | IV6: West Bengal | IW6: Tamil Nadu | IX6: Karnataka | IY6: Telangana | IZ6: Delhi | JA6: West Bengal | JB6: Karnataka | JC6: Karnataka | JD6: Tamil Nadu | JE6: Delhi | JF6: Delhi | JG6: Maharashtra | JH6: Telangana | JI6: Karnataka | JJ6: Delhi | JK6: Tamil Nadu | JL6: Maharashtra | JM6: Karnataka | JN6: Maharashtra | JO6: Tamil Nadu | JP6: Telangana | JQ6: West Bengal | JR6: Maharashtra | JS6: West Bengal | JT6: Maharashtra | JU6: Tamil Nadu | JV6: West Bengal | JW6: West Bengal | JX6: West Bengal | JY6: Telangana | JZ6: Delhi | KA6: Tamil Nadu | KB6: Tamil Nadu | KC6: Karnataka | KD6: Karnataka | KE6: West Bengal | KF6: Telangana | KG6: Telangana | KH6: Tamil Nadu | KI6: Telangana | KJ6: Delhi | KK6: Telangana | KL6: Tamil Nadu | KM6: Telangana | KN6: Telangana | KO6: Tamil Nadu | KP6: Delhi | KQ6: Delhi | KR6: Maharashtra | KS6: Delhi | KT6: Tamil Nadu | KU6: Tamil Nadu | KV6: Delhi | KW6: Tamil Nadu | KX6: Tamil Nadu | KY6: West Bengal | KZ6: Maharashtra | LA6: Maharashtra | LB6: Karnataka | LC6: Tamil Nadu | LD6: West Bengal | LE6: Tamil Nadu | LF6: Delhi | LG6: West Bengal | LH6: Delhi | LI6: Karnataka | LJ6: Tamil Nadu | LK6: West Bengal | LL6: Tamil Nadu | LM6: Delhi | LN6: Delhi | LO6: Maharashtra | LP6: Maharashtra | LQ6: Maharashtra | LR6: Maharashtra | LS6: Maharashtra | LT6: Delhi | LU6: Tamil Nadu | LV6: Karnataka | LW6: Maharashtra | LX6: West Bengal | LY6: Tamil Nadu | LZ6: Tamil Nadu | MA6: West Bengal | MB6: Maharashtra | MC6: Tamil Nadu | MD6: Tamil Nadu | ME6: Karnataka | MF6: Karnataka | MG6: Karnataka | MH6: Tamil Nadu | MI6: Telangana | MJ6: West Bengal | MK6: West Bengal | ML6: West Bengal | MM6: Delhi | MN6: Tamil Nadu | MO6: Tamil Nadu | MP6: Telangana | MQ6: Delhi | MR6: West Bengal | MS6: Maharashtra | MT6: West Bengal | MU6: Telangana | MV6: Maharashtra | MW6: Delhi | MX6: Telangana | MY6: Delhi | MZ6: Tamil Nadu | NA6: West Bengal | NB6: West Bengal | NC6: Delhi | ND6: Telangana | NE6: Tamil Nadu | NF6: Tamil Nadu | NG6: West Bengal | NH6: Delhi | NI6: Delhi
A7: Sales Channel | B7: Mobile App | C7: Website | D7: Marketplace | E7: Website | F7: Marketplace | G7: Website | H7: Mobile App | I7: Website | J7: Website | K7: Website | L7: Mobile App | M7: Website | N7: Mobile App | O7: Marketplace | P7: Website | Q7: Mobile App | R7: Mobile App | S7: Website | T7: Marketplace | U7: Mobile App | V7: Website | W7: Marketplace | X7: Mobile App | Y7: Mobile App | Z7: Marketplace | AA7: Marketplace | AB7: Website | AC7: Website | AD7: Mobile App | AE7: Marketplace | AF7: Marketplace | AG7: Marketplace | AH7: Mobile App | AI7: Marketplace | AJ7: Marketplace | AK7: Mobile App | AL7: Website | AM7: Website | AN7: Mobile App | AO7: Marketplace | AP7: Mobile App | AQ7: Website | AR7: Website | AS7: Mobile App | AT7: Mobile App | AU7: Website | AV7: Mobile App | AW7: Website | AX7: Mobile App | AY7: Mobile App | AZ7: Website | BA7: Mobile App | BB7: Website | BC7: Website | BD7: Mobile App | BE7: Mobile App | BF7: Website | BG7: Marketplace | BH7: Website | BI7: Marketplace | BJ7: Marketplace | BK7: Mobile App | BL7: Mobile App | BM7: Website | BN7: Marketplace | BO7: Mobile App | BP7: Mobile App | BQ7: Mobile App | BR7: Mobile App | BS7: Mobile App | BT7: Marketplace | BU7: Marketplace | BV7: Marketplace | BW7: Marketplace | BX7: Marketplace | BY7: Mobile App | BZ7: Marketplace | CA7: Website | CB7: Mobile App | CC7: Marketplace | CD7: Marketplace | CE7: Marketplace | CF7: Mobile App | CG7: Mobile App | CH7: Mobile App | CI7: Marketplace | CJ7: Mobile App | CK7: Marketplace | CL7: Marketplace | CM7: Mobile App | CN7: Website | CO7: Website | CP7: Mobile App | CQ7: Website | CR7: Marketplace | CS7: Marketplace | CT7: Mobile App | CU7: Website | CV7: Marketplace | CW7: Mobile App | CX7: Website | CY7: Website | CZ7: Marketplace | DA7: Marketplace | DB7: Mobile App | DC7: Marketplace | DD7: Website | DE7: Marketplace | DF7: Mobile App | DG7: Mobile App | DH7: Mobile App | DI7: Website | DJ7: Website | DK7: Website | DL7: Website | DM7: Website | DN7: Marketplace | DO7: Website | DP7: Website | DQ7: Marketplace | DR7: Website | DS7: Mobile App | DT7: Website | DU7: Website | DV7: Mobile App | DW7: Mobile App | DX7: Mobile App | DY7: Mobile App | DZ7: Mobile App | EA7: Marketplace | EB7: Mobile App | EC7: Mobile App | ED7: Marketplace | EE7: Marketplace | EF7: Website | EG7: Marketplace | EH7: Website | EI7: Marketplace | EJ7: Marketplace | EK7: Website | EL7: Marketplace | EM7: Website | EN7: Mobile App | EO7: Marketplace | EP7: Website | EQ7: Marketplace | ER7: Website | ES7: Website | ET7: Mobile App | EU7: Mobile App | EV7: Website | EW7: Marketplace | EX7: Website | EY7: Website | EZ7: Marketplace | FA7: Marketplace | FB7: Marketplace | FC7: Website | FD7: Website | FE7: Mobile App | FF7: Website | FG7: Marketplace | FH7: Mobile App | FI7: Mobile App | FJ7: Marketplace | FK7: Mobile App | FL7: Mobile App | FM7: Marketplace | FN7: Mobile App | FO7: Mobile App | FP7: Marketplace | FQ7: Mobile App | FR7: Mobile App | FS7: Marketplace | FT7: Marketplace | FU7: Marketplace | FV7: Marketplace | FW7: Website | FX7: Mobile App | FY7: Marketplace | FZ7: Mobile App | GA7: Mobile App | GB7: Website | GC7: Marketplace | GD7: Marketplace | GE7: Mobile App | GF7: Website | GG7: Website | GH7: Mobile App | GI7: Marketplace | GJ7: Website | GK7: Marketplace | GL7: Website | GM7: Mobile App | GN7: Website | GO7: Website | GP7: Mobile App | GQ7: Website | GR7: Website | GS7: Mobile App | GT7: Mobile App | GU7: Marketplace | GV7: Mobile App | GW7: Mobile App | GX7: Marketplace | GY7: Mobile App | GZ7: Website | HA7: Website | HB7: Mobile App | HC7: Marketplace | HD7: Marketplace | HE7: Mobile App | HF7: Marketplace | HG7: Website | HH7: Marketplace | HI7: Marketplace | HJ7: Mobile App | HK7: Mobile App | HL7: Website | HM7: Website | HN7: Mobile App | HO7: Website | HP7: Mobile App | HQ7: Website | HR7: Mobile App | HS7: Marketplace | HT7: Marketplace | HU7: Marketplace | HV7: Marketplace | HW7: Marketplace | HX7: Website | HY7: Website | HZ7: Marketplace | IA7: Marketplace | IB7: Website | IC7: Website | ID7: Marketplace | IE7: Website | IF7: Marketplace | IG7: Mobile App | IH7: Website | II7: Mobile App | IJ7: Marketplace | IK7: Website | IL7: Website | IM7: Website | IN7: Mobile App | IO7: Website | IP7: Mobile App | IQ7: Website | IR7: Mobile App | IS7: Marketplace | IT7: Website | IU7: Marketplace | IV7: Marketplace | IW7: Website | IX7: Marketplace | IY7: Mobile App | IZ7: Website | JA7: Website | JB7: Marketplace | JC7: Website | JD7: Marketplace | JE7: Mobile App | JF7: Marketplace | JG7: Marketplace | JH7: Website | JI7: Marketplace | JJ7: Website | JK7: Mobile App | JL7: Website | JM7: Mobile App | JN7: Mobile App | JO7: Mobile App | JP7: Website | JQ7: Marketplace | JR7: Mobile App | JS7: Mobile App | JT7: Mobile App | JU7: Mobile App | JV7: Marketplace | JW7: Marketplace | JX7: Website | JY7: Mobile App | JZ7: Marketplace | KA7: Marketplace | KB7: Marketplace | KC7: Marketplace | KD7: Mobile App | KE7: Marketplace | KF7: Mobile App | KG7: Marketplace | KH7: Website | KI7: Mobile App | KJ7: Website | KK7: Marketplace | KL7: Mobile App | KM7: Marketplace | KN7: Mobile App | KO7: Website | KP7: Website | KQ7: Mobile App | KR7: Marketplace | KS7: Website | KT7: Website | KU7: Website | KV7: Website | KW7: Website | KX7: Website | KY7: Website | KZ7: Marketplace | LA7: Website | LB7: Website | LC7: Website | LD7: Mobile App | LE7: Website | LF7: Marketplace | LG7: Mobile App | LH7: Website | LI7: Website | LJ7: Website | LK7: Marketplace | LL7: Website | LM7: Website | LN7: Marketplace | LO7: Website | LP7: Marketplace | LQ7: Mobile App | LR7: Website | LS7: Mobile App | LT7: Website | LU7: Website | LV7: Marketplace | LW7: Website | LX7: Website | LY7: Marketplace | LZ7: Marketplace | MA7: Website | MB7: Mobile App | MC7: Mobile App | MD7: Website | ME7: Marketplace | MF7: Mobile App | MG7: Marketplace | MH7: Website | MI7: Mobile App | MJ7: Mobile App | MK7: Website | ML7: Website | MM7: Website | MN7: Marketplace | MO7: Marketplace | MP7: Marketplace | MQ7: Mobile App | MR7: Marketplace | MS7: Marketplace | MT7: Mobile App | MU7: Mobile App | MV7: Website | MW7: Mobile App | MX7: Website | MY7: Marketplace | MZ7: Website | NA7: Mobile App | NB7: Mobile App | NC7: Website | ND7: Mobile App | NE7: Marketplace | NF7: Mobile App | NG7: Website | NH7: Marketplace | NI7: Marketplace
A8: Payment Method | B8: Credit Card | C8: Debit Card | D8: Debit Card | E8: Cash on Delivery | F8: Credit Card | G8: Net Banking | H8: UPI | I8: Credit Card | J8: Debit Card | K8: Cash on Delivery | L8: Cash on Delivery | M8: UPI | N8: Cash on Delivery | O8: Cash on Delivery | P8: Credit Card | Q8: Net Banking | R8: UPI | S8: Credit Card | T8: Net Banking | U8: Credit Card | V8: Credit Card | W8: Cash on Delivery | X8: Net Banking | Y8: UPI | Z8: UPI | AA8: Net Banking | AB8: Cash on Delivery | AC8: Debit Card | AD8: Credit Card | AE8: Cash on Delivery | AF8: Net Banking | AG8: Credit Card | AH8: UPI | AI8: Debit Card | AJ8: UPI | AK8: Net Banking | AL8: Credit Card | AM8: Net Banking | AN8: Credit Card | AO8: Cash on Delivery | AP8: Debit Card | AQ8: Cash on Delivery | AR8: Cash on Delivery | AS8: Net Banking | AT8: Debit Card | AU8: Credit Card | AV8: Credit Card | AW8: UPI | AX8: Credit Card | AY8: Net Banking | AZ8: Cash on Delivery | BA8: Cash on Delivery | BB8: Debit Card | BC8: Credit Card | BD8: Net Banking | BE8: Debit Card | BF8: Net Banking | BG8: Net Banking | BH8: Net Banking | BI8: Net Banking | BJ8: Credit Card | BK8: Net Banking | BL8: Cash on Delivery | BM8: Net Banking | BN8: UPI | BO8: UPI | BP8: Cash on Delivery | BQ8: Credit Card | BR8: Credit Card | BS8: Debit Card | BT8: Cash on Delivery | BU8: Net Banking | BV8: Cash on Delivery | BW8: Debit Card | BX8: Cash on Delivery | BY8: Debit Card | BZ8: Credit Card | CA8: Net Banking | CB8: Debit Card | CC8: UPI | CD8: Credit Card | CE8: UPI | CF8: Credit Card | CG8: Net Banking | CH8: UPI | CI8: Credit Card | CJ8: Net Banking | CK8: Debit Card | CL8: Net Banking | CM8: Debit Card | CN8: Credit Card | CO8: Net Banking | CP8: Net Banking | CQ8: Credit Card | CR8: Net Banking | CS8: Debit Card | CT8: Net Banking | CU8: Cash on Delivery | CV8: Debit Card | CW8: UPI | CX8: Credit Card | CY8: Cash on Delivery | CZ8: Cash on Delivery | DA8: Credit Card | DB8: Credit Card | DC8: Debit Card | DD8: Net Banking | DE8: Credit Card | DF8: Net Banking | DG8: UPI | DH8: Cash on Delivery | DI8: Net Banking | DJ8: Cash on Delivery | DK8: Net Banking | DL8: UPI | DM8: Credit Card | DN8: UPI | DO8: Credit Card | DP8: Credit Card | DQ8: Cash on Delivery | DR8: UPI | DS8: Net Banking | DT8: UPI | DU8: Cash on Delivery | DV8: Credit Card | DW8: Debit Card | DX8: Debit Card | DY8: Cash on Delivery | DZ8: Net Banking | EA8: Net Banking | EB8: Debit Card | EC8: Net Banking | ED8: Debit Card | EE8: Credit Card | EF8: Cash on Delivery | EG8: Net Banking | EH8: Debit Card | EI8: UPI | EJ8: Net Banking | EK8: Credit Card | EL8: Credit Card | EM8: UPI | EN8: Net Banking | EO8: Debit Card | EP8: Credit Card | EQ8: Debit Card | ER8: Credit Card | ES8: Debit Card | ET8: UPI | EU8: Cash on Delivery | EV8: UPI | EW8: UPI | EX8: Cash on Delivery | EY8: Cash on Delivery | EZ8: Net Banking | FA8: Net Banking | FB8: UPI | FC8: Credit Card | FD8: Credit Card | FE8: Net Banking | FF8: Net Banking | FG8: Credit Card | FH8: Credit Card | FI8: Credit Card | FJ8: Debit Card | FK8: Cash on Delivery | FL8: Net Banking | FM8: Credit Card | FN8: UPI | FO8: Credit Card | FP8: Debit Card | FQ8: UPI | FR8: Debit Card | FS8: Debit Card | FT8: Cash on Delivery | FU8: Cash on Delivery | FV8: Debit Card | FW8: Debit Card | FX8: Cash on Delivery | FY8: UPI | FZ8: Cash on Delivery | GA8: Net Banking | GB8: Cash on Delivery | GC8: UPI | GD8: Net Banking | GE8: Credit Card | GF8: UPI | GG8: Net Banking | GH8: Net Banking | GI8: Credit Card | GJ8: Net Banking | GK8: UPI | GL8: UPI | GM8: Debit Card | GN8: Credit Card | GO8: Net Banking | GP8: UPI | GQ8: Credit Card | GR8: UPI | GS8: Debit Card | GT8: Net Banking | GU8: UPI | GV8: Credit Card | GW8: UPI | GX8: UPI | GY8: Cash on Delivery | GZ8: Cash on Delivery | HA8: Debit Card | HB8: Net Banking | HC8: Credit Card | HD8: Credit Card | HE8: UPI | HF8: Net Banking | HG8: Debit Card | HH8: Cash on Delivery | HI8: Net Banking | HJ8: Credit Card | HK8: Debit Card | HL8: Net Banking | HM8: Cash on Delivery | HN8: Net Banking | HO8: UPI | HP8: Net Banking | HQ8: Debit Card | HR8: UPI | HS8: Cash on Delivery | HT8: UPI | HU8: Cash on Delivery | HV8: UPI | HW8: Net Banking | HX8: Cash on Delivery | HY8: Cash on Delivery | HZ8: Debit Card | IA8: Credit Card | IB8: UPI | IC8: Debit Card | ID8: Credit Card | IE8: Credit Card | IF8: UPI | IG8: UPI | IH8: Credit Card | II8: Debit Card | IJ8: Credit Card | IK8: Debit Card | IL8: Cash on Delivery | IM8: Net Banking | IN8: Cash on Delivery | IO8: Credit Card | IP8: Debit Card | IQ8: Debit Card | IR8: Cash on Delivery | IS8: Net Banking | IT8: Net Banking | IU8: Debit Card | IV8: UPI | IW8: Credit Card | IX8: Credit Card | IY8: Cash on Delivery | IZ8: Debit Card | JA8: Credit Card | JB8: Credit Card | JC8: Debit Card | JD8: Cash on Delivery | JE8: Cash on Delivery | JF8: Net Banking | JG8: Cash on Delivery | JH8: UPI | JI8: Cash on Delivery | JJ8: UPI | JK8: Net Banking | JL8: Debit Card | JM8: UPI | JN8: UPI | JO8: Net Banking | JP8: Net Banking | JQ8: Net Banking | JR8: Debit Card | JS8: Cash on Delivery | JT8: Cash on Delivery | JU8: Credit Card | JV8: UPI | JW8: Net Banking | JX8: UPI | JY8: UPI | JZ8: Cash on Delivery | KA8: Credit Card | KB8: Cash on Delivery | KC8: Net Banking | KD8: Debit Card | KE8: Cash on Delivery | KF8: Debit Card | KG8: Net Banking | KH8: UPI | KI8: Cash on Delivery | KJ8: Net Banking | KK8: Cash on Delivery | KL8: Cash on Delivery | KM8: Credit Card | KN8: Credit Card | KO8: Cash on Delivery | KP8: Credit Card | KQ8: Net Banking | KR8: Credit Card | KS8: Cash on Delivery | KT8: UPI | KU8: Net Banking | KV8: Net Banking | KW8: Net Banking | KX8: UPI | KY8: Net Banking | KZ8: Credit Card | LA8: Cash on Delivery | LB8: Debit Card | LC8: Cash on Delivery | LD8: Credit Card | LE8: UPI | LF8: UPI | LG8: UPI | LH8: Net Banking | LI8: UPI | LJ8: Debit Card | LK8: UPI | LL8: Debit Card | LM8: Credit Card | LN8: Debit Card | LO8: Credit Card | LP8: Net Banking | LQ8: UPI | LR8: Cash on Delivery | LS8: Credit Card | LT8: UPI | LU8: Debit Card | LV8: Cash on Delivery | LW8: Debit Card | LX8: UPI | LY8: Credit Card | LZ8: Credit Card | MA8: Cash on Delivery | MB8: Net Banking | MC8: Net Banking | MD8: Cash on Delivery | ME8: Credit Card | MF8: Cash on Delivery | MG8: Credit Card | MH8: Net Banking | MI8: Debit Card | MJ8: Credit Card | MK8: UPI | ML8: Debit Card | MM8: Cash on Delivery | MN8: Net Banking | MO8: UPI | MP8: Cash on Delivery | MQ8: Credit Card | MR8: Credit Card | MS8: Cash on Delivery | MT8: UPI | MU8: UPI | MV8: Debit Card | MW8: Net Banking | MX8: Net Banking | MY8: Debit Card | MZ8: Credit Card | NA8: Cash on Delivery | NB8: UPI | NC8: UPI | ND8: UPI | NE8: Debit Card | NF8: Net Banking | NG8: Net Banking | NH8: Credit Card | NI8: Net Banking
A9: Product Category | B9: Home & Kitchen | C9: Sports | D9: Fashion | E9: Sports | F9: Fashion | G9: Home & Kitchen | H9: Fashion | I9: Fashion | J9: Fashion | K9: Electronics | L9: Electronics | M9: Electronics | N9: Home & Kitchen | O9: Sports | P9: Beauty | Q9: Fashion | R9: Fashion | S9: Home & Kitchen | T9: Fashion | U9: Electronics | V9: Beauty | W9: Books | X9: Fashion | Y9: Electronics | Z9: Books | AA9: Beauty | AB9: Books | AC9: Electronics | AD9: Sports | AE9: Sports | AF9: Books | AG9: Home & Kitchen | AH9: Books | AI9: Fashion | AJ9: Fashion | AK9: Sports | AL9: Home & Kitchen | AM9: Electronics | AN9: Fashion | AO9: Sports | AP9: Beauty | AQ9: Sports | AR9: Fashion | AS9: Fashion | AT9: Sports | AU9: Electronics | AV9: Books | AW9: Fashion | AX9: Sports | AY9: Sports | AZ9: Books | BA9: Beauty | BB9: Electronics | BC9: Beauty | BD9: Books | BE9: Books | BF9: Beauty | BG9: Books | BH9: Sports | BI9: Books | BJ9: Sports | BK9: Home & Kitchen | BL9: Books | BM9: Beauty | BN9: Fashion | BO9: Books | BP9: Fashion | BQ9: Sports | BR9: Home & Kitchen | BS9: Electronics | BT9: Home & Kitchen | BU9: Books | BV9: Fashion | BW9: Fashion | BX9: Fashion | BY9: Beauty | BZ9: Sports | CA9: Electronics | CB9: Books | CC9: Beauty | CD9: Electronics | CE9: Fashion | CF9: Fashion | CG9: Electronics | CH9: Sports | CI9: Electronics | CJ9: Beauty | CK9: Beauty | CL9: Electronics | CM9: Beauty | CN9: Beauty | CO9: Sports | CP9: Beauty | CQ9: Home & Kitchen | CR9: Books | CS9: Fashion | CT9: Home & Kitchen | CU9: Sports | CV9: Electronics | CW9: Beauty | CX9: Sports | CY9: Beauty | CZ9: Electronics | DA9: Sports | DB9: Sports | DC9: Sports | DD9: Books | DE9: Beauty | DF9: Books | DG9: Fashion | DH9: Fashion | DI9: Beauty | DJ9: Books | DK9: Electronics | DL9: Sports | DM9: Sports | DN9: Beauty | DO9: Fashion | DP9: Fashion | DQ9: Sports | DR9: Beauty | DS9: Books | DT9: Fashion | DU9: Books | DV9: Fashion | DW9: Home & Kitchen | DX9: Fashion | DY9: Beauty | DZ9: Beauty | EA9: Books | EB9: Fashion | EC9: Electronics | ED9: Books | EE9: Home & Kitchen | EF9: Books | EG9: Books | EH9: Fashion | EI9: Home & Kitchen | EJ9: Books | EK9: Electronics | EL9: Electronics | EM9: Beauty | EN9: Home & Kitchen | EO9: Beauty | EP9: Books | EQ9: Home & Kitchen | ER9: Electronics | ES9: Electronics | ET9: Fashion | EU9: Home & Kitchen | EV9: Books | EW9: Beauty | EX9: Beauty | EY9: Books | EZ9: Sports | FA9: Fashion | FB9: Beauty | FC9: Fashion | FD9: Home & Kitchen | FE9: Electronics | FF9: Fashion | FG9: Beauty | FH9: Fashion | FI9: Sports | FJ9: Fashion | FK9: Home & Kitchen | FL9: Electronics | FM9: Fashion | FN9: Beauty | FO9: Fashion | FP9: Beauty | FQ9: Home & Kitchen | FR9: Beauty | FS9: Electronics | FT9: Beauty | FU9: Beauty | FV9: Electronics | FW9: Books | FX9: Fashion | FY9: Beauty | FZ9: Electronics | GA9: Home & Kitchen | GB9: Electronics | GC9: Home & Kitchen | GD9: Books | GE9: Fashion | GF9: Electronics | GG9: Beauty | GH9: Electronics | GI9: Home & Kitchen | GJ9: Electronics | GK9: Sports | GL9: Electronics | GM9: Sports | GN9: Books | GO9: Electronics | GP9: Sports | GQ9: Home & Kitchen | GR9: Electronics | GS9: Books | GT9: Electronics | GU9: Electronics | GV9: Books | GW9: Home & Kitchen | GX9: Fashion | GY9: Beauty | GZ9: Books | HA9: Electronics | HB9: Books | HC9: Home & Kitchen | HD9: Books | HE9: Beauty | HF9: Electronics | HG9: Beauty | HH9: Beauty | HI9: Fashion | HJ9: Fashion | HK9: Fashion | HL9: Beauty | HM9: Home & Kitchen | HN9: Beauty | HO9: Fashion | HP9: Fashion | HQ9: Fashion | HR9: Books | HS9: Electronics | HT9: Beauty | HU9: Sports | HV9: Beauty | HW9: Fashion | HX9: Electronics | HY9: Fashion | HZ9: Home & Kitchen | IA9: Fashion | IB9: Beauty | IC9: Beauty | ID9: Sports | IE9: Electronics | IF9: Sports | IG9: Books | IH9: Books | II9: Books | IJ9: Home & Kitchen | IK9: Beauty | IL9: Home & Kitchen | IM9: Fashion | IN9: Fashion | IO9: Fashion | IP9: Books | IQ9: Sports | IR9: Fashion | IS9: Books | IT9: Books | IU9: Beauty | IV9: Electronics | IW9: Home & Kitchen | IX9: Beauty | IY9: Books | IZ9: Sports | JA9: Electronics | JB9: Books | JC9: Electronics | JD9: Electronics | JE9: Sports | JF9: Beauty | JG9: Sports | JH9: Books | JI9: Beauty | JJ9: Beauty | JK9: Beauty | JL9: Beauty | JM9: Sports | JN9: Beauty | JO9: Books | JP9: Home & Kitchen | JQ9: Electronics | JR9: Fashion | JS9: Electronics | JT9: Sports | JU9: Electronics | JV9: Beauty | JW9: Sports | JX9: Home & Kitchen | JY9: Books | JZ9: Fashion | KA9: Sports | KB9: Beauty | KC9: Fashion | KD9: Books | KE9: Books | KF9: Fashion | KG9: Fashion | KH9: Books | KI9: Beauty | KJ9: Electronics | KK9: Books | KL9: Sports | KM9: Electronics | KN9: Electronics | KO9: Electronics | KP9: Beauty | KQ9: Books | KR9: Books | KS9: Sports | KT9: Beauty | KU9: Fashion | KV9: Home & Kitchen | KW9: Beauty | KX9: Electronics | KY9: Fashion | KZ9: Fashion | LA9: Fashion | LB9: Beauty | LC9: Beauty | LD9: Electronics | LE9: Sports | LF9: Electronics | LG9: Electronics | LH9: Home & Kitchen | LI9: Sports | LJ9: Home & Kitchen | LK9: Electronics | LL9: Beauty | LM9: Fashion | LN9: Home & Kitchen | LO9: Beauty | LP9: Sports | LQ9: Beauty | LR9: Beauty | LS9: Beauty | LT9: Beauty | LU9: Home & Kitchen | LV9: Electronics | LW9: Home & Kitchen | LX9: Beauty | LY9: Beauty | LZ9: Sports | MA9: Electronics | MB9: Electronics | MC9: Fashion | MD9: Books | ME9: Fashion | MF9: Sports | MG9: Home & Kitchen | MH9: Electronics | MI9: Books | MJ9: Beauty | MK9: Sports | ML9: Electronics | MM9: Sports | MN9: Fashion | MO9: Home & Kitchen | MP9: Home & Kitchen | MQ9: Books | MR9: Sports | MS9: Fashion | MT9: Sports | MU9: Electronics | MV9: Books | MW9: Home & Kitchen | MX9: Electronics | MY9: Beauty | MZ9: Books | NA9: Fashion | NB9: Electronics | NC9: Electronics | ND9: Books | NE9: Books | NF9: Beauty | NG9: Fashion | NH9: Sports | NI9: Fashion
A10: Product Name | B10: Mixer Grinder | C10: Football | D10: Sneakers | E10: Yoga Mat | F10: Jacket | G10: Bedsheet | H10: Sneakers | I10: Sneakers | J10: T-Shirt | K10: Headphones | L10: Headphones | M10: Smartwatch | N10: Bedsheet | O10: Yoga Mat | P10: Shampoo | Q10: Jacket | R10: Jacket | S10: Curtains | T10: Jacket | U10: Smartwatch | V10: Lipstick | W10: Fiction Novel | X10: Sneakers | Y10: Smartwatch | Z10: Comics | AA10: Perfume | AB10: Fiction Novel | AC10: Smartwatch | AD10: Football | AE10: Cricket Bat | AF10: Textbook | AG10: Bedsheet | AH10: Comics | AI10: T-Shirt | AJ10: T-Shirt | AK10: Football | AL10: Curtains | AM10: Laptop | AN10: T-Shirt | AO10: Football | AP10: Face Cream | AQ10: Football | AR10: T-Shirt | AS10: T-Shirt | AT10: Cricket Bat | AU10: Smartwatch | AV10: Textbook | AW10: Jeans | AX10: Football | AY10: Cricket Bat | AZ10: Textbook | BA10: Face Cream | BB10: Headphones | BC10: Face Cream | BD10: Textbook | BE10: Fiction Novel | BF10: Face Cream | BG10: Textbook | BH10: Yoga Mat | BI10: Textbook | BJ10: Yoga Mat | BK10: Bedsheet | BL10: Biography | BM10: Face Cream | BN10: T-Shirt | BO10: Textbook | BP10: Jacket | BQ10: Cricket Bat | BR10: Curtains | BS10: Smartphone | BT10: Bedsheet | BU10: Fiction Novel | BV10: Jacket | BW10: Sneakers | BX10: Sneakers | BY10: Lipstick | BZ10: Football | CA10: Laptop | CB10: Textbook | CC10: Lipstick | CD10: Headphones | CE10: Jeans | CF10: Jacket | CG10: Laptop | CH10: Football | CI10: Headphones | CJ10: Lipstick | CK10: Perfume | CL10: Headphones | CM10: Perfume | CN10: Perfume | CO10: Yoga Mat | CP10: Shampoo | CQ10: Bedsheet | CR10: Comics | CS10: Jacket | CT10: Mixer Grinder | CU10: Football | CV10: Laptop | CW10: Perfume | CX10: Yoga Mat | CY10: Lipstick | CZ10: Smartphone | DA10: Yoga Mat | DB10: Cricket Bat | DC10: Dumbbells | DD10: Textbook | DE10: Perfume | DF10: Fiction Novel | DG10: T-Shirt | DH10: Sneakers | DI10: Shampoo | DJ10: Textbook | DK10: Laptop | DL10: Dumbbells | DM10: Cricket Bat | DN10: Face Cream | DO10: T-Shirt | DP10: Jacket | DQ10: Cricket Bat | DR10: Lipstick | DS10: Textbook | DT10: Sneakers | DU10: Fiction Novel | DV10: T-Shirt | DW10: Bedsheet | DX10: Jacket | DY10: Shampoo | DZ10: Shampoo | EA10: Comics | EB10: Jacket | EC10: Smartwatch | ED10: Fiction Novel | EE10: Curtains | EF10: Comics | EG10: Textbook | EH10: T-Shirt | EI10: Mixer Grinder | EJ10: Textbook | EK10: Smartwatch | EL10: Laptop | EM10: Lipstick | EN10: Bedsheet | EO10: Lipstick | EP10: Comics | EQ10: Mixer Grinder | ER10: Laptop | ES10: Smartphone | ET10: T-Shirt | EU10: Mixer Grinder | EV10: Fiction Novel | EW10: Shampoo | EX10: Face Cream | EY10: Textbook | EZ10: Football | FA10: Sneakers | FB10: Lipstick | FC10: Jeans | FD10: Bedsheet | FE10: Laptop | FF10: Jeans | FG10: Shampoo | FH10: Sneakers | FI10: Cricket Bat | FJ10: Sneakers | FK10: Bedsheet | FL10: Headphones | FM10: Jacket | FN10: Face Cream | FO10: Jacket | FP10: Lipstick | FQ10: Bedsheet | FR10: Shampoo | FS10: Smartwatch | FT10: Lipstick | FU10: Perfume | FV10: Smartwatch | FW10: Comics | FX10: Jeans | FY10: Shampoo | FZ10: Smartphone | GA10: Cookware Set | GB10: Smartwatch | GC10: Cookware Set | GD10: Comics | GE10: Jeans | GF10: Smartwatch | GG10: Shampoo | GH10: Headphones | GI10: Mixer Grinder | GJ10: Smartwatch | GK10: Cricket Bat | GL10: Laptop | GM10: Football | GN10: Biography | GO10: Headphones | GP10: Dumbbells | GQ10: Curtains | GR10: Smartwatch | GS10: Comics | GT10: Laptop | GU10: Smartphone | GV10: Comics | GW10: Curtains | GX10: T-Shirt | GY10: Perfume | GZ10: Textbook | HA10: Laptop | HB10: Biography | HC10: Cookware Set | HD10: Comics | HE10: Shampoo | HF10: Smartwatch | HG10: Shampoo | HH10: Face Cream | HI10: Jacket | HJ10: Jeans | HK10: T-Shirt | HL10: Perfume | HM10: Mixer Grinder | HN10: Face Cream | HO10: Sneakers | HP10: Jeans | HQ10: Sneakers | HR10: Comics | HS10: Laptop | HT10: Perfume | HU10: Cricket Bat | HV10: Shampoo | HW10: Jacket | HX10: Smartwatch | HY10: Jeans | HZ10: Cookware Set | IA10: Jacket | IB10: Perfume | IC10: Face Cream | ID10: Dumbbells | IE10: Smartphone | IF10: Dumbbells | IG10: Fiction Novel | IH10: Biography | II10: Fiction Novel | IJ10: Mixer Grinder | IK10: Shampoo | IL10: Bedsheet | IM10: T-Shirt | IN10: T-Shirt | IO10: Jeans | IP10: Biography | IQ10: Cricket Bat | IR10: T-Shirt | IS10: Textbook | IT10: Fiction Novel | IU10: Shampoo | IV10: Smartwatch | IW10: Bedsheet | IX10: Lipstick | IY10: Textbook | IZ10: Dumbbells | JA10: Headphones | JB10: Fiction Novel | JC10: Laptop | JD10: Smartphone | JE10: Yoga Mat | JF10: Perfume | JG10: Cricket Bat | JH10: Fiction Novel | JI10: Face Cream | JJ10: Perfume | JK10: Perfume | JL10: Shampoo | JM10: Football | JN10: Face Cream | JO10: Biography | JP10: Cookware Set | JQ10: Headphones | JR10: Sneakers | JS10: Smartwatch | JT10: Football | JU10: Smartwatch | JV10: Lipstick | JW10: Yoga Mat | JX10: Mixer Grinder | JY10: Textbook | JZ10: Sneakers | KA10: Yoga Mat | KB10: Shampoo | KC10: T-Shirt | KD10: Fiction Novel | KE10: Fiction Novel | KF10: T-Shirt | KG10: Sneakers | KH10: Comics | KI10: Shampoo | KJ10: Laptop | KK10: Textbook | KL10: Yoga Mat | KM10: Laptop | KN10: Smartphone | KO10: Laptop | KP10: Shampoo | KQ10: Fiction Novel | KR10: Comics | KS10: Dumbbells | KT10: Lipstick | KU10: T-Shirt | KV10: Curtains | KW10: Face Cream | KX10: Smartphone | KY10: Sneakers | KZ10: Jacket | LA10: T-Shirt | LB10: Perfume | LC10: Perfume | LD10: Headphones | LE10: Yoga Mat | LF10: Smartwatch | LG10: Laptop | LH10: Bedsheet | LI10: Yoga Mat | LJ10: Cookware Set | LK10: Smartwatch | LL10: Shampoo | LM10: Jacket | LN10: Bedsheet | LO10: Shampoo | LP10: Yoga Mat | LQ10: Face Cream | LR10: Lipstick | LS10: Face Cream | LT10: Perfume | LU10: Curtains | LV10: Smartwatch | LW10: Mixer Grinder | LX10: Lipstick | LY10: Perfume | LZ10: Cricket Bat | MA10: Smartwatch | MB10: Headphones | MC10: Jeans | MD10: Fiction Novel | ME10: Sneakers | MF10: Dumbbells | MG10: Mixer Grinder | MH10: Smartphone | MI10: Fiction Novel | MJ10: Face Cream | MK10: Football | ML10: Headphones | MM10: Yoga Mat | MN10: Jeans | MO10: Bedsheet | MP10: Bedsheet | MQ10: Comics | MR10: Yoga Mat | MS10: T-Shirt | MT10: Yoga Mat | MU10: Headphones | MV10: Biography | MW10: Bedsheet | MX10: Laptop | MY10: Shampoo | MZ10: Textbook | NA10: Sneakers | NB10: Laptop | NC10: Smartphone | ND10: Biography | NE10: Comics | NF10: Perfume | NG10: Jacket | NH10: Yoga Mat | NI10: Jeans
A11: Brand | B11: BrandA | C11: BrandD | D11: BrandE | E11: BrandA | F11: BrandA | G11: BrandE | H11: BrandC | I11: BrandB | J11: BrandD | K11: BrandB | L11: BrandE | M11: BrandA | N11: BrandA | O11: BrandD | P11: BrandA | Q11: BrandA | R11: BrandD | S11: BrandD | T11: BrandE | U11: BrandA | V11: BrandA | W11: BrandE | X11: BrandC | Y11: BrandC | Z11: BrandC | AA11: BrandE | AB11: BrandA | AC11: BrandE | AD11: BrandE | AE11: BrandC | AF11: BrandB | AG11: BrandA | AH11: BrandC | AI11: BrandB | AJ11: BrandB | AK11: BrandD | AL11: BrandA | AM11: BrandB | AN11: BrandC | AO11: BrandD | AP11: BrandA | AQ11: BrandE | AR11: BrandC | AS11: BrandB | AT11: BrandB | AU11: BrandC | AV11: BrandB | AW11: BrandD | AX11: BrandA | AY11: BrandD | AZ11: BrandE | BA11: BrandA | BB11: BrandA | BC11: BrandC | BD11: BrandC | BE11: BrandE | BF11: BrandE | BG11: BrandC | BH11: BrandC | BI11: BrandD | BJ11: BrandB | BK11: BrandC | BL11: BrandC | BM11: BrandD | BN11: BrandD | BO11: BrandE | BP11: BrandE | BQ11: BrandB | BR11: BrandB | BS11: BrandA | BT11: BrandE | BU11: BrandC | BV11: BrandE | BW11: BrandC | BX11: BrandE | BY11: BrandD | BZ11: BrandB | CA11: BrandB | CB11: BrandA | CC11: BrandE | CD11: BrandD | CE11: BrandC | CF11: BrandB | CG11: BrandB | CH11: BrandD | CI11: BrandE | CJ11: BrandE | CK11: BrandA | CL11: BrandB | CM11: BrandE | CN11: BrandD | CO11: BrandC | CP11: BrandD | CQ11: BrandB | CR11: BrandD | CS11: BrandA | CT11: BrandB | CU11: BrandA | CV11: BrandB | CW11: BrandC | CX11: BrandA | CY11: BrandB | CZ11: BrandE | DA11: BrandA | DB11: BrandA | DC11: BrandC | DD11: BrandD | DE11: BrandB | DF11: BrandB | DG11: BrandE | DH11: BrandE | DI11: BrandB | DJ11: BrandE | DK11: BrandC | DL11: BrandB | DM11: BrandE | DN11: BrandB | DO11: BrandD | DP11: BrandA | DQ11: BrandB | DR11: BrandA | DS11: BrandE | DT11: BrandA | DU11: BrandB | DV11: BrandD | DW11: BrandB | DX11: BrandE | DY11: BrandA | DZ11: BrandC | EA11: BrandB | EB11: BrandD | EC11: BrandE | ED11: BrandA | EE11: BrandE | EF11: BrandB | EG11: BrandE | EH11: BrandA | EI11: BrandB | EJ11: BrandE | EK11: BrandD | EL11: BrandB | EM11: BrandB | EN11: BrandC | EO11: BrandA | EP11: BrandC | EQ11: BrandE | ER11: BrandD | ES11: BrandC | ET11: BrandB | EU11: BrandE | EV11: BrandE | EW11: BrandC | EX11: BrandC | EY11: BrandD | EZ11: BrandA | FA11: BrandC | FB11: BrandC | FC11: BrandE | FD11: BrandA | FE11: BrandB | FF11: BrandD | FG11: BrandD | FH11: BrandC | FI11: BrandC | FJ11: BrandA | FK11: BrandC | FL11: BrandE | FM11: BrandB | FN11: BrandA | FO11: BrandB | FP11: BrandB | FQ11: BrandE | FR11: BrandA | FS11: BrandA | FT11: BrandA | FU11: BrandA | FV11: BrandE | FW11: BrandC | FX11: BrandB | FY11: BrandA | FZ11: BrandC | GA11: BrandC | GB11: BrandB | GC11: BrandE | GD11: BrandD | GE11: BrandD | GF11: BrandE | GG11: BrandD | GH11: BrandC | GI11: BrandC | GJ11: BrandA | GK11: BrandE | GL11: BrandB | GM11: BrandA | GN11: BrandA | GO11: BrandD | GP11: BrandC | GQ11: BrandA | GR11: BrandA | GS11: BrandB | GT11: BrandC | GU11: BrandE | GV11: BrandA | GW11: BrandB | GX11: BrandE | GY11: BrandB | GZ11: BrandC | HA11: BrandB | HB11: BrandC | HC11: BrandE | HD11: BrandD | HE11: BrandC | HF11: BrandB | HG11: BrandC | HH11: BrandB | HI11: BrandA | HJ11: BrandC | HK11: BrandD | HL11: BrandE | HM11: BrandB | HN11: BrandC | HO11: BrandB | HP11: BrandD | HQ11: BrandE | HR11: BrandA | HS11: BrandE | HT11: BrandB | HU11: BrandE | HV11: BrandB | HW11: BrandD | HX11: BrandB | HY11: BrandC | HZ11: BrandB | IA11: BrandC | IB11: BrandE | IC11: BrandE | ID11: BrandC | IE11: BrandE | IF11: BrandA | IG11: BrandD | IH11: BrandA | II11: BrandA | IJ11: BrandD | IK11: BrandE | IL11: BrandC | IM11: BrandE | IN11: BrandB | IO11: BrandE | IP11: BrandA | IQ11: BrandA | IR11: BrandA | IS11: BrandD | IT11: BrandD | IU11: BrandC | IV11: BrandB | IW11: BrandE | IX11: BrandE | IY11: BrandC | IZ11: BrandD | JA11: BrandC | JB11: BrandE | JC11: BrandB | JD11: BrandA | JE11: BrandD | JF11: BrandC | JG11: BrandD | JH11: BrandE | JI11: BrandC | JJ11: BrandE | JK11: BrandB | JL11: BrandC | JM11: BrandB | JN11: BrandA | JO11: BrandA | JP11: BrandE | JQ11: BrandA | JR11: BrandA | JS11: BrandD | JT11: BrandB | JU11: BrandA | JV11: BrandE | JW11: BrandC | JX11: BrandC | JY11: BrandA | JZ11: BrandC | KA11: BrandC | KB11: BrandA | KC11: BrandA | KD11: BrandD | KE11: BrandE | KF11: BrandB | KG11: BrandC | KH11: BrandA | KI11: BrandE | KJ11: BrandA | KK11: BrandC | KL11: BrandB | KM11: BrandD | KN11: BrandB | KO11: BrandA | KP11: BrandA | KQ11: BrandE | KR11: BrandC | KS11: BrandC | KT11: BrandB | KU11: BrandE | KV11: BrandD | KW11: BrandE | KX11: BrandD | KY11: BrandE | KZ11: BrandE | LA11: BrandB | LB11: BrandE | LC11: BrandC | LD11: BrandB | LE11: BrandC | LF11: BrandB | LG11: BrandE | LH11: BrandE | LI11: BrandA | LJ11: BrandC | LK11: BrandA | LL11: BrandE | LM11: BrandE | LN11: BrandE | LO11: BrandD | LP11: BrandC | LQ11: BrandC | LR11: BrandE | LS11: BrandB | LT11: BrandB | LU11: BrandD | LV11: BrandD | LW11: BrandC | LX11: BrandA | LY11: BrandA | LZ11: BrandB | MA11: BrandD | MB11: BrandE | MC11: BrandC | MD11: BrandC | ME11: BrandA | MF11: BrandD | MG11: BrandE | MH11: BrandD | MI11: BrandD | MJ11: BrandC | MK11: BrandD | ML11: BrandA | MM11: BrandB | MN11: BrandB | MO11: BrandE | MP11: BrandD | MQ11: BrandC | MR11: BrandD | MS11: BrandD | MT11: BrandB | MU11: BrandB | MV11: BrandE | MW11: BrandC | MX11: BrandE | MY11: BrandA | MZ11: BrandE | NA11: BrandC | NB11: BrandD | NC11: BrandD | ND11: BrandC | NE11: BrandC | NF11: BrandC | NG11: BrandA | NH11: BrandD | NI11: BrandE
A12: Units Sold | B12: 7 | C12: 9 | D12: 6 | E12: 1 | F12: 7 | G12: 3 | H12: 5 | I12: 4 | J12: 5 | K12: 5 | L12: 6 | M12: 6 | N12: 8 | O12: 8 | P12: 9 | Q12: 8 | R12: 2 | S12: 1 | T12: 2 | U12: 2 | V12: 3 | W12: 7 | X12: 2 | Y12: 1 | Z12: 6 | AA12: 9 | AB12: 3 | AC12: 6 | AD12: 3 | AE12: 1 | AF12: 5 | AG12: 4 | AH12: 7 | AI12: 6 | AJ12: 7 | AK12: 5 | AL12: 4 | AM12: 7 | AN12: 7 | AO12: 6 | AP12: 8 | AQ12: 4 | AR12: 5 | AS12: 4 | AT12: 1 | AU12: 8 | AV12: 1 | AW12: 5 | AX12: 6 | AY12: 6 | AZ12: 3 | BA12: 5 | BB12: 8 | BC12: 2 | BD12: 6 | BE12: 9 | BF12: 8 | BG12: 8 | BH12: 7 | BI12: 6 | BJ12: 2 | BK12: 2 | BL12: 8 | BM12: 1 | BN12: 6 | BO12: 6 | BP12: 4 | BQ12: 3 | BR12: 3 | BS12: 1 | BT12: 3 | BU12: 4 | BV12: 5 | BW12: 3 | BX12: 5 | BY12: 3 | BZ12: 6 | CA12: 6 | CB12: 8 | CC12: 2 | CD12: 1 | CE12: 4 | CF12: 7 | CG12: 3 | CH12: 5 | CI12: 3 | CJ12: 9 | CK12: 4 | CL12: 3 | CM12: 2 | CN12: 9 | CO12: 4 | CP12: 3 | CQ12: 7 | CR12: 8 | CS12: 2 | CT12: 7 | CU12: 5 | CV12: 3 | CW12: 5 | CX12: 2 | CY12: 6 | CZ12: 1 | DA12: 4 | DB12: 6 | DC12: 9 | DD12: 2 | DE12: 7 | DF12: 6 | DG12: 2 | DH12: 8 | DI12: 7 | DJ12: 5 | DK12: 5 | DL12: 7 | DM12: 9 | DN12: 9 | DO12: 9 | DP12: 6 | DQ12: 6 | DR12: 3 | DS12: 1 | DT12: 7 | DU12: 4 | DV12: 1 | DW12: 6 | DX12: 6 | DY12: 1 | DZ12: 2 | EA12: 4 | EB12: 2 | EC12: 1 | ED12: 7 | EE12: 8 | EF12: 6 | EG12: 4 | EH12: 6 | EI12: 3 | EJ12: 8 | EK12: 2 | EL12: 5 | EM12: 1 | EN12: 2 | EO12: 4 | EP12: 6 | EQ12: 8 | ER12: 8 | ES12: 6 | ET12: 4 | EU12: 8 | EV12: 8 | EW12: 1 | EX12: 4 | EY12: 4 | EZ12: 7 | FA12: 7 | FB12: 8 | FC12: 7 | FD12: 8 | FE12: 9 | FF12: 3 | FG12: 3 | FH12: 4 | FI12: 7 | FJ12: 9 | FK12: 8 | FL12: 5 | FM12: 7 | FN12: 5 | FO12: 7 | FP12: 1 | FQ12: 1 | FR12: 3 | FS12: 2 | FT12: 7 | FU12: 2 | FV12: 4 | FW12: 2 | FX12: 6 | FY12: 8 | FZ12: 4 | GA12: 5 | GB12: 4 | GC12: 3 | GD12: 5 | GE12: 9 | GF12: 7 | GG12: 8 | GH12: 8 | GI12: 8 | GJ12: 7 | GK12: 1 | GL12: 4 | GM12: 5 | GN12: 6 | GO12: 4 | GP12: 2 | GQ12: 8 | GR12: 7 | GS12: 6 | GT12: 5 | GU12: 8 | GV12: 1 | GW12: 1 | GX12: 7 | GY12: 9 | GZ12: 8 | HA12: 2 | HB12: 9 | HC12: 6 | HD12: 2 | HE12: 3 | HF12: 8 | HG12: 1 | HH12: 7 | HI12: 7 | HJ12: 1 | HK12: 8 | HL12: 4 | HM12: 5 | HN12: 2 | HO12: 3 | HP12: 3 | HQ12: 2 | HR12: 7 | HS12: 7 | HT12: 4 | HU12: 8 | HV12: 1 | HW12: 1 | HX12: 5 | HY12: 6 | HZ12: 3 | IA12: 6 | IB12: 4 | IC12: 7 | ID12: 9 | IE12: 8 | IF12: 5 | IG12: 6 | IH12: 6 | II12: 7 | IJ12: 8 | IK12: 9 | IL12: 3 | IM12: 1 | IN12: 5 | IO12: 7 | IP12: 6 | IQ12: 4 | IR12: 2 | IS12: 1 | IT12: 4 | IU12: 4 | IV12: 1 | IW12: 4 | IX12: 1 | IY12: 1 | IZ12: 1 | JA12: 8 | JB12: 8 | JC12: 2 | JD12: 7 | JE12: 8 | JF12: 7 | JG12: 5 | JH12: 9 | JI12: 7 | JJ12: 2 | JK12: 6 | JL12: 2 | JM12: 1 | JN12: 7 | JO12: 2 | JP12: 1 | JQ12: 3 | JR12: 4 | JS12: 4 | JT12: 5 | JU12: 7 | JV12: 4 | JW12: 1 | JX12: 4 | JY12: 1 | JZ12: 3 | KA12: 2 | KB12: 9 | KC12: 9 | KD12: 8 | KE12: 8 | KF12: 1 | KG12: 8 | KH12: 3 | KI12: 5 | KJ12: 5 | KK12: 8 | KL12: 8 | KM12: 6 | KN12: 6 | KO12: 2 | KP12: 6 | KQ12: 5 | KR12: 6 | KS12: 1 | KT12: 3 | KU12: 1 | KV12: 5 | KW12: 3 | KX12: 2 | KY12: 8 | KZ12: 3 | LA12: 1 | LB12: 3 | LC12: 8 | LD12: 6 | LE12: 2 | LF12: 6 | LG12: 5 | LH12: 3 | LI12: 1 | LJ12: 4 | LK12: 1 | LL12: 9 | LM12: 7 | LN12: 3 | LO12: 8 | LP12: 1 | LQ12: 1 | LR12: 8 | LS12: 6 | LT12: 9 | LU12: 9 | LV12: 6 | LW12: 8 | LX12: 3 | LY12: 3 | LZ12: 5 | MA12: 3 | MB12: 1 | MC12: 3 | MD12: 9 | ME12: 2 | MF12: 4 | MG12: 7 | MH12: 1 | MI12: 9 | MJ12: 2 | MK12: 5 | ML12: 1 | MM12: 5 | MN12: 1 | MO12: 4 | MP12: 6 | MQ12: 9 | MR12: 8 | MS12: 5 | MT12: 6 | MU12: 8 | MV12: 7 | MW12: 2 | MX12: 9 | MY12: 4 | MZ12: 8 | NA12: 7 | NB12: 5 | NC12: 7 | ND12: 5 | NE12: 8 | NF12: 6 | NG12: 5 | NH12: 9 | NI12: 1
A13: Unit Price | B13: 2843.87 | C13: 2525.23 | D13: 3474.34 | E13: 1008.79 | F13: 3511.47 | G13: 3189.55 | H13: 3030.42 | I13: 2310.83 | J13: 1098.04 | K13: 1780.66 | L13: 3205.25 | M13: 272.35 | N13: 3160.9 | O13: 1074.27 | P13: 705.59 | Q13: 595.45 | R13: 254.91 | S13: 2165.81 | T13: 990.3 | U13: 3959.31 | V13: 2361.58 | W13: 680.86 | X13: 2801.74 | Y13: 3606.31 | Z13: 3018.94 | AA13: 444.29 | AB13: 3599.15 | AC13: 3206.63 | AD13: 759.47 | AE13: 349.38 | AF13: 2295.65 | AG13: 750.74 | AH13: 3363.18 | AI13: 1529.59 | AJ13: 3664.64 | AK13: 2327.9 | AL13: 853.29 | AM13: 687.46 | AN13: 2369.42 | AO13: 3083.25 | AP13: 3158.8 | AQ13: 1211.67 | AR13: 936.35 | AS13: 214.51 | AT13: 2764.92 | AU13: 444.79 | AV13: 1769.93 | AW13: 2466.48 | AX13: 3757.87 | AY13: 1350.44 | AZ13: 2668.52 | BA13: 2534.07 | BB13: 1428.62 | BC13: 3723.19 | BD13: 3402.72 | BE13: 1012.33 | BF13: 2122.36 | BG13: 3128.25 | BH13: 319.56 | BI13: 2645.71 | BJ13: 1041.2 | BK13: 2773.21 | BL13: 3769.71 | BM13: 330.13 | BN13: 1380.66 | BO13: 1836.98 | BP13: 3612.15 | BQ13: 3854.71 | BR13: 1859.84 | BS13: 3037.61 | BT13: 2196.89 | BU13: 2220.46 | BV13: 1220.68 | BW13: 985.28 | BX13: 2291.86 | BY13: 262.25 | BZ13: 3642.91 | CA13: 751.69 | CB13: 997.34 | CC13: 2145.36 | CD13: 2883.94 | CE13: 518.56 | CF13: 1373.12 | CG13: 3879.4 | CH13: 3370.52 | CI13: 343.33 | CJ13: 1938.76 | CK13: 1611.52 | CL13: 1368.86 | CM13: 1249.94 | CN13: 501.79 | CO13: 1362.08 | CP13: 315.75 | CQ13: 3156.71 | CR13: 1683.18 | CS13: 1859.03 | CT13: 3590.34 | CU13: 181.03 | CV13: 3781.22 | CW13: 1063.01 | CX13: 564.31 | CY13: 2076.84 | CZ13: 1820.02 | DA13: 1110.59 | DB13: 2257.77 | DC13: 1206.38 | DD13: 3621.09 | DE13: 978.54 | DF13: 3554.77 | DG13: 2303.71 | DH13: 3339.68 | DI13: 2894.46 | DJ13: 2832.28 | DK13: 1398.73 | DL13: 1050.5 | DM13: 961.91 | DN13: 3450.19 | DO13: 3308.64 | DP13: 1846.21 | DQ13: 659.76 | DR13: 1621.67 | DS13: 2534.47 | DT13: 1899.45 | DU13: 3153.73 | DV13: 3990.85 | DW13: 1919.66 | DX13: 1809.29 | DY13: 912.67 | DZ13: 402.91 | EA13: 3565.41 | EB13: 1766.42 | EC13: 2063.05 | ED13: 3680.23 | EE13: 3138.72 | EF13: 652.43 | EG13: 2326.87 | EH13: 1852.67 | EI13: 3219.26 | EJ13: 2938.3 | EK13: 2808.06 | EL13: 1461.1 | EM13: 3249.11 | EN13: 764.56 | EO13: 1442.15 | EP13: 445.71 | EQ13: 1054.73 | ER13: 3346.08 | ES13: 3800.77 | ET13: 1322.72 | EU13: 1168.39 | EV13: 1227.59 | EW13: 1219.22 | EX13: 288.33 | EY13: 3718.63 | EZ13: 972.74 | FA13: 1767.02 | FB13: 187.29 | FC13: 2964.96 | FD13: 3795.01 | FE13: 3159.22 | FF13: 1357.77 | FG13: 1104.31 | FH13: 2836.21 | FI13: 174.09 | FJ13: 388.26 | FK13: 2211.17 | FL13: 2329.38 | FM13: 658.07 | FN13: 2125.75 | FO13: 898.62 | FP13: 508.81 | FQ13: 1730.41 | FR13: 778.85 | FS13: 1372.59 | FT13: 1148.65 | FU13: 487.23 | FV13: 496.18 | FW13: 894.01 | FX13: 344.65 | FY13: 2561.86 | FZ13: 1256.21 | GA13: 1227.02 | GB13: 1428.19 | GC13: 2701.77 | GD13: 3501.94 | GE13: 3072.48 | GF13: 982.56 | GG13: 953.07 | GH13: 1291.11 | GI13: 3656.59 | GJ13: 2257.55 | GK13: 2975.54 | GL13: 1719.71 | GM13: 633.43 | GN13: 809.49 | GO13: 3335.32 | GP13: 2401.63 | GQ13: 3240.98 | GR13: 3907.73 | GS13: 1477.55 | GT13: 620.13 | GU13: 3519.2 | GV13: 2250.49 | GW13: 556.53 | GX13: 324.38 | GY13: 2677.09 | GZ13: 284.52 | HA13: 3960.56 | HB13: 265.58 | HC13: 1861.43 | HD13: 601.53 | HE13: 800.89 | HF13: 1504.45 | HG13: 3082.45 | HH13: 2102.27 | HI13: 2605.92 | HJ13: 3942.92 | HK13: 1822.29 | HL13: 1868.8 | HM13: 2532.27 | HN13: 2711.66 | HO13: 240.6 | HP13: 647.32 | HQ13: 533.25 | HR13: 2472.29 | HS13: 2165.86 | HT13: 1126.3 | HU13: 2045.09 | HV13: 900.78 | HW13: 2660.56 | HX13: 3156.54 | HY13: 3197.13 | HZ13: 2469.51 | IA13: 384.88 | IB13: 1258.15 | IC13: 509.1 | ID13: 670.06 | IE13: 3784.12 | IF13: 3098.44 | IG13: 220.79 | IH13: 1936.66 | II13: 1396.71 | IJ13: 2695.39 | IK13: 2661.11 | IL13: 967.49 | IM13: 619.73 | IN13: 2850.33 | IO13: 636.59 | IP13: 257.2 | IQ13: 2547.52 | IR13: 3256.02 | IS13: 3391.76 | IT13: 2008.45 | IU13: 3143.2 | IV13: 2740.46 | IW13: 2046.51 | IX13: 2588.64 | IY13: 3251.27 | IZ13: 1681.85 | JA13: 3253.02 | JB13: 2429.26 | JC13: 788.72 | JD13: 245.03 | JE13: 2254.78 | JF13: 3383.31 | JG13: 640.82 | JH13: 3472.58 | JI13: 730.15 | JJ13: 3428.64 | JK13: 3967.1 | JL13: 2948.33 | JM13: 3171.36 | JN13: 3978.5 | JO13: 1335.36 | JP13: 1126.5 | JQ13: 464.42 | JR13: 3708.51 | JS13: 641.93 | JT13: 1853.11 | JU13: 313.51 | JV13: 2785.81 | JW13: 3625.42 | JX13: 640.37 | JY13: 3708.38 | JZ13: 1923.58 | KA13: 2071.04 | KB13: 2632.88 | KC13: 1259.77 | KD13: 1300.31 | KE13: 3581.12 | KF13: 202.49 | KG13: 1392.5 | KH13: 2284.27 | KI13: 3593.46 | KJ13: 3320.88 | KK13: 3610.33 | KL13: 3277.19 | KM13: 1628.56 | KN13: 2715.13 | KO13: 3957.02 | KP13: 1019.05 | KQ13: 1651.11 | KR13: 681.36 | KS13: 3910.66 | KT13: 487.45 | KU13: 3581.58 | KV13: 1935.68 | KW13: 1382.11 | KX13: 1984.38 | KY13: 1375.47 | KZ13: 2032.79 | LA13: 2430.36 | LB13: 1553.98 | LC13: 2993.25 | LD13: 2716.48 | LE13: 610.31 | LF13: 2354.67 | LG13: 3245.77 | LH13: 1789.86 | LI13: 2743.75 | LJ13: 1333.99 | LK13: 2044.41 | LL13: 3216.56 | LM13: 1020.23 | LN13: 2165.72 | LO13: 1297.59 | LP13: 1219.7 | LQ13: 3354.81 | LR13: 3905.57 | LS13: 1288.31 | LT13: 3740.3 | LU13: 2454.59 | LV13: 2247.37 | LW13: 437.36 | LX13: 3644.78 | LY13: 3986.78 | LZ13: 3116.22 | MA13: 1448.62 | MB13: 3775.07 | MC13: 2189.4 | MD13: 2969.7 | ME13: 3904.44 | MF13: 3871.21 | MG13: 2568.26 | MH13: 1574.59 | MI13: 3191.56 | MJ13: 1374.23 | MK13: 1480.66 | ML13: 445.38 | MM13: 2072.32 | MN13: 559.4 | MO13: 589.44 | MP13: 3773.04 | MQ13: 1890.53 | MR13: 150.72 | MS13: 2523.25 | MT13: 845 | MU13: 1160.51 | MV13: 2172.24 | MW13: 1294.84 | MX13: 775.77 | MY13: 2751.14 | MZ13: 2536.88 | NA13: 2838.06 | NB13: 977.43 | NC13: 1550.03 | ND13: 529.59 | NE13: 598.44 | NF13: 1128.91 | NG13: 1287.55 | NH13: 2190.39 | NI13: 2432.17
A14: Discount % | B14: 0 | C14: 5 | D14: 15 | E14: 15 | F14: 20 | G14: 10 | H14: 10 | I14: 10 | J14: 15 | K14: 20 | L14: 0 | M14: 5 | N14: 0 | O14: 15 | P14: 10 | Q14: 5 | R14: 15 | S14: 15 | T14: 15 | U14: 5 | V14: 5 | W14: 20 | X14: 20 | Y14: 0 | Z14: 5 | AA14: 5 | AB14: 5 | AC14: 20 | AD14: 15 | AE14: 10 | AF14: 20 | AG14: 5 | AH14: 20 | AI14: 0 | AJ14: 5 | AK14: 0 | AL14: 5 | AM14: 20 | AN14: 15 | AO14: 10 | AP14: 0 | AQ14: 20 | AR14: 15 | AS14: 20 | AT14: 0 | AU14: 10 | AV14: 20 | AW14: 5 | AX14: 15 | AY14: 20 | AZ14: 5 | BA14: 10 | BB14: 10 | BC14: 5 | BD14: 15 | BE14: 20 | BF14: 0 | BG14: 15 | BH14: 10 | BI14: 10 | BJ14: 15 | BK14: 10 | BL14: 5 | BM14: 15 | BN14: 0 | BO14: 5 | BP14: 20 | BQ14: 5 | BR14: 15 | BS14: 5 | BT14: 0 | BU14: 0 | BV14: 20 | BW14: 10 | BX14: 15 | BY14: 10 | BZ14: 0 | CA14: 0 | CB14: 5 | CC14: 20 | CD14: 20 | CE14: 20 | CF14: 5 | CG14: 20 | CH14: 10 | CI14: 5 | CJ14: 20 | CK14: 10 | CL14: 10 | CM14: 10 | CN14: 5 | CO14: 15 | CP14: 20 | CQ14: 10 | CR14: 15 | CS14: 20 | CT14: 20 | CU14: 10 | CV14: 5 | CW14: 15 | CX14: 15 | CY14: 20 | CZ14: 10 | DA14: 20 | DB14: 20 | DC14: 10 | DD14: 0 | DE14: 15 | DF14: 20 | DG14: 20 | DH14: 0 | DI14: 5 | DJ14: 0 | DK14: 0 | DL14: 20 | DM14: 15 | DN14: 0 | DO14: 5 | DP14: 10 | DQ14: 0 | DR14: 0 | DS14: 5 | DT14: 15 | DU14: 0 | DV14: 0 | DW14: 5 | DX14: 0 | DY14: 0 | DZ14: 10 | EA14: 20 | EB14: 10 | EC14: 0 | ED14: 5 | EE14: 20 | EF14: 10 | EG14: 15 | EH14: 5 | EI14: 10 | EJ14: 15 | EK14: 0 | EL14: 15 | EM14: 10 | EN14: 0 | EO14: 15 | EP14: 15 | EQ14: 0 | ER14: 15 | ES14: 0 | ET14: 5 | EU14: 10 | EV14: 5 | EW14: 20 | EX14: 20 | EY14: 20 | EZ14: 0 | FA14: 15 | FB14: 5 | FC14: 5 | FD14: 5 | FE14: 20 | FF14: 5 | FG14: 15 | FH14: 20 | FI14: 10 | FJ14: 10 | FK14: 10 | FL14: 20 | FM14: 20 | FN14: 15 | FO14: 0 | FP14: 0 | FQ14: 10 | FR14: 10 | FS14: 5 | FT14: 15 | FU14: 15 | FV14: 15 | FW14: 15 | FX14: 10 | FY14: 0 | FZ14: 10 | GA14: 15 | GB14: 10 | GC14: 15 | GD14: 20 | GE14: 0 | GF14: 10 | GG14: 20 | GH14: 15 | GI14: 15 | GJ14: 10 | GK14: 15 | GL14: 15 | GM14: 20 | GN14: 5 | GO14: 20 | GP14: 0 | GQ14: 0 | GR14: 10 | GS14: 10 | GT14: 5 | GU14: 0 | GV14: 15 | GW14: 5 | GX14: 10 | GY14: 10 | GZ14: 15 | HA14: 10 | HB14: 10 | HC14: 0 | HD14: 20 | HE14: 0 | HF14: 20 | HG14: 5 | HH14: 20 | HI14: 20 | HJ14: 0 | HK14: 20 | HL14: 20 | HM14: 15 | HN14: 0 | HO14: 5 | HP14: 5 | HQ14: 0 | HR14: 10 | HS14: 0 | HT14: 20 | HU14: 10 | HV14: 5 | HW14: 10 | HX14: 20 | HY14: 10 | HZ14: 0 | IA14: 5 | IB14: 0 | IC14: 15 | ID14: 20 | IE14: 15 | IF14: 0 | IG14: 5 | IH14: 0 | II14: 20 | IJ14: 10 | IK14: 10 | IL14: 0 | IM14: 0 | IN14: 5 | IO14: 5 | IP14: 0 | IQ14: 20 | IR14: 20 | IS14: 20 | IT14: 5 | IU14: 0 | IV14: 10 | IW14: 5 | IX14: 0 | IY14: 15 | IZ14: 5 | JA14: 15 | JB14: 15 | JC14: 20 | JD14: 0 | JE14: 0 | JF14: 20 | JG14: 0 | JH14: 15 | JI14: 0 | JJ14: 10 | JK14: 0 | JL14: 15 | JM14: 20 | JN14: 20 | JO14: 5 | JP14: 15 | JQ14: 20 | JR14: 5 | JS14: 0 | JT14: 10 | JU14: 0 | JV14: 20 | JW14: 10 | JX14: 20 | JY14: 20 | JZ14: 15 | KA14: 20 | KB14: 5 | KC14: 15 | KD14: 0 | KE14: 15 | KF14: 5 | KG14: 15 | KH14: 20 | KI14: 20 | KJ14: 0 | KK14: 5 | KL14: 15 | KM14: 0 | KN14: 20 | KO14: 5 | KP14: 0 | KQ14: 20 | KR14: 15 | KS14: 5 | KT14: 5 | KU14: 15 | KV14: 20 | KW14: 10 | KX14: 10 | KY14: 15 | KZ14: 10 | LA14: 15 | LB14: 15 | LC14: 10 | LD14: 0 | LE14: 10 | LF14: 15 | LG14: 0 | LH14: 0 | LI14: 15 | LJ14: 5 | LK14: 0 | LL14: 20 | LM14: 10 | LN14: 5 | LO14: 0 | LP14: 5 | LQ14: 0 | LR14: 10 | LS14: 15 | LT14: 10 | LU14: 5 | LV14: 15 | LW14: 20 | LX14: 0 | LY14: 20 | LZ14: 10 | MA14: 10 | MB14: 10 | MC14: 20 | MD14: 10 | ME14: 10 | MF14: 10 | MG14: 10 | MH14: 5 | MI14: 20 | MJ14: 0 | MK14: 0 | ML14: 10 | MM14: 15 | MN14: 20 | MO14: 20 | MP14: 0 | MQ14: 15 | MR14: 5 | MS14: 10 | MT14: 15 | MU14: 0 | MV14: 20 | MW14: 15 | MX14: 0 | MY14: 20 | MZ14: 5 | NA14: 20 | NB14: 20 | NC14: 10 | ND14: 5 | NE14: 0 | NF14: 20 | NG14: 0 | NH14: 20 | NI14: 20
A15: Total Price | B15: =B12*B13 -> 19907.09 | C15: =C12*C13 -> 22727.07 | D15: =D12*D13 -> 20846.04 | E15: =E12*E13 -> 1008.79 | F15: =F12*F13 -> 24580.29 | G15: =G12*G13 -> 9568.65 | H15: =H12*H13 -> 15152.1 | I15: =I12*I13 -> 9243.32 | ... NI15: =NI12*NI13 -> 2432.17
A16: Price Category | B16: =IF(B15>=15000,"High price","Low price") -> High price | C16: =IF(C15>=15000,"High price","Low price") -> High price | D16: =IF(D15>=15000,"High price","Low price") -> High price | E16: =IF(E15>=15000,"High price","Low price") -> Low price | F16: =IF(F15>=15000,"High price","Low price") -> High price | G16: =IF(G15>=15000,"High price","Low price") -> Low price | H16: =IF(H15>=15000,"High price","Low price") -> High price | I16: =IF(I15>=15000,"High price","Low price") -> Low price | ... NI16: =IF(NI15>=15000,"High price","Low price") -> Low price
A17: Discount Category | B17: {=_xlfn.IFS(B14>=10,"HIGH",B14>=5,"MEDIUM",B14<5,"LOW")} -> LOW | C17: {=_xlfn.IFS(C14>=10,"HIGH",C14>=5,"MEDIUM",C14<5,"LOW")} -> MEDIUM | D17: {=_xlfn.IFS(D14>=10,"HIGH",D14>=5,"MEDIUM",D14<5,"LOW")} -> HIGH | E17: {=_xlfn.IFS(E14>=10,"HIGH",E14>=5,"MEDIUM",E14<5,"LOW")} -> HIGH | F17: {=_xlfn.IFS(F14>=10,"HIGH",F14>=5,"MEDIUM",F14<5,"LOW")} -> HIGH | G17: {=_xlfn.IFS(G14>=10,"HIGH",G14>=5,"MEDIUM",G14<5,"LOW")} -> HIGH | H17: {=_xlfn.IFS(H14>=10,"HIGH",H14>=5,"MEDIUM",H14<5,"LOW")} -> HIGH | I17: {=_xlfn.IFS(I14>=10,"HIGH",I14>=5,"MEDIUM",I14<5,"LOW")} -> HIGH | ... NI17: {=_xlfn.IFS(NI14>=10,"HIGH",NI14>=5,"MEDIUM",NI14<5,"LOW")} -> HIGH
A18: Unit Category | B18: =IF(B12>8,"High",IF(B12>4,"Medium","Low")) -> Medium | C18: =IF(C12>8,"High",IF(C12>4,"Medium","Low")) -> High | D18: =IF(D12>8,"High",IF(D12>4,"Medium","Low")) -> Medium | E18: =IF(E12>8,"High",IF(E12>4,"Medium","Low")) -> Low | F18: =IF(F12>8,"High",IF(F12>4,"Medium","Low")) -> Medium | G18: =IF(G12>8,"High",IF(G12>4,"Medium","Low")) -> Low | H18: =IF(H12>8,"High",IF(H12>4,"Medium","Low")) -> Medium | I18: =IF(I12>8,"High",IF(I12>4,"Medium","Low")) -> Low | ... NI18: =IF(NI12>8,"High",IF(NI12>4,"Medium","Low")) -> Low
A20: Customer ID | B20: 1270
A21: Unit Price | B21: =HLOOKUP(B20,A2:NI18,12,0) -> 1008.79
